[
  {
    "事件标题": "凉茂被曹操征辟为司空掾",
    "时间": "建安年间",
    "地点": "许都",
    "相关人物": [
      "凉茂",
      "曹操"
    ],
    "原文": "凉茂字伯方，山阳昌邑人也。少好学，论议常据经典，以处是非。太祖辟为司空掾，举高第，补侍御史。",
    "事件翻译": "凉茂字伯方，是山阳郡昌邑县人。年轻时好学，议论时常依据经典来判断是非。太祖曹操征召他为司空掾，考试名列前茅，补任侍御史。",
    "std_start_year": 196,
    "涉及的集团": [
      "qiao_jun_cao_xiahou"
    ],
    "所属事件": [],
    "地理信息": [
      "豫州:颍川郡:许县"
    ],
    "是否本传": true
  },
  {
    "事件标题": "凉茂任泰山太守招抚流民",
    "时间": "建安年间",
    "地点": "泰山郡",
    "相关人物": [
      "凉茂"
    ],
    "原文": "时泰山多盗贼，以茂为泰山太守，旬月之间，襁负而至者千馀家。[博物记曰：襁，织缕为之，广八寸，长尺二，以约小儿於背上，负之而行。]",
    "事件翻译": "当时泰山郡有很多盗贼，朝廷任命凉茂为泰山太守，一个月之内，背着婴儿前来归附的有一千多家。[博物记说：襁，是用丝线编织而成的，宽八寸，长一尺二寸，用来把小孩绑在背上，背着行走。]",
    "std_start_year": 196,
    "涉及的集团": [],
    "所属事件": [],
    "地理信息": [
      "兖州:山阳郡"
    ],
    "是否本传": true
  },
  {
    "事件标题": "凉茂转任乐浪太守被公孙度扣留",
    "时间": "建安年间",
    "地点": "辽东",
    "相关人物": [
      "凉茂",
      "公孙度"
    ],
    "原文": "转为乐浪太守。公孙度在辽东，擅留茂，不遣之官，然茂终不为屈。",
    "事件翻译": "凉茂转任乐浪太守。公孙度在辽东，擅自扣留凉茂，不让他去上任，但凉茂始终不屈服。",
    "std_start_year": 200,
    "涉及的集团": [],
    "所属事件": [],
    "地理信息": [
      "幽州:辽东郡"
    ],
    "是否本传": true
  },
  {
    "事件标题": "公孙度欲攻邺城询问凉茂",
    "时间": "建安十二年",
    "地点": "辽东",
    "相关人物": [
      "公孙度",
      "凉茂"
    ],
    "原文": "度谓茂及诸将曰：闻曹公远征，邺无守备，今吾欲以步卒三万，骑万匹，直指邺，谁能御之？诸将皆曰：然。[臣松之案此传云公孙度闻曹公远征，邺无守备，则太祖定邺后也。案度传，度以建安九年卒，太祖亦以此年定邺，自后远征，唯有北征柳城耳。征柳城之年，度已不复在矣。]又顾谓茂曰：於君意何如？茂答曰：比者海内大乱，社稷将倾，将军拥十万之众，安坐而观成败，夫为人臣者，固若是邪！曹公忧国家之危败，愍百姓之苦毒，率义兵为天下诛残贼，功高而德广，可谓无二矣。以海内初定，民始安集，故未责将军之罪耳！而将军乃欲称兵西向，则存亡之效，不崇朝而决。将军其勉之！诸将闻茂言，皆震动。良久，度曰：凉君言是也。",
    "事件翻译": "公孙度对凉茂和众将领说：听说曹公远征，邺城没有守备，现在我打算率领步兵三万、骑兵一万，直取邺城，谁能抵挡？众将都说：对。[臣裴松之按：此传称公孙度听说曹公远征，邺城没有守备，那么是在太祖平定邺城之后。按公孙度传，公孙度在建安九年去世，太祖也在这一年平定邺城，此后远征，只有北征柳城。征柳城那年，公孙度已经不在世了。]又回头对凉茂说：您意下如何？凉茂回答说：近来天下大乱，社稷将倾，将军拥有十万之众，安坐观望成败，作为臣子，难道应该这样吗！曹公忧虑国家的危败，怜悯百姓的苦难，率领义兵为天下诛除残贼，功高德广，可以说是独一无二了。因为天下刚刚平定，百姓才开始安定聚集，所以没有追究将军的罪过！而将军竟想举兵西向，那么存亡的结局，不到一个早晨就能决定。将军请自勉！众将听了凉茂的话，都震动失色。过了很久，公孙度说：凉君说得对。",
    "std_start_year": 207,
    "涉及的集团": [],
    "所属事件": [],
    "地理信息": [
      "幽州:辽东郡"
    ],
    "是否本传": true
  },
  {
    "事件标题": "凉茂被征召为魏郡太守、甘陵相",
    "时间": "建安年间",
    "地点": "邺城",
    "相关人物": [
      "凉茂"
    ],
    "原文": "后徵迁为魏郡太守、甘陵相，所在有绩。",
    "事件翻译": "后来凉茂被征召升任魏郡太守、甘陵相，所任之处都有政绩。",
    "std_start_year": 210,
    "涉及的集团": [],
    "所属事件": [],
    "地理信息": [
      "冀州:魏郡:邺县"
    ],
    "是否本传": true
  },
  {
    "事件标题": "凉茂任五官将长史、左军师",
    "时间": "建安年间",
    "地点": "邺城",
    "相关人物": [
      "凉茂",
      "曹丕"
    ],
    "原文": "文帝为五官将，茂以选为长史，迁左军师。",
    "事件翻译": "文帝曹丕任五官中郎将时，凉茂被选为长史，升任左军师。",
    "std_start_year": 211,
    "涉及的集团": [
      "qiao_jun_cao_xiahou"
    ],
    "所属事件": [],
    "地理信息": [
      "冀州:魏郡:邺县"
    ],
    "是否本传": true
  },
  {
    "事件标题": "凉茂任尚书仆射、中尉奉常",
    "时间": "建安十八年",
    "地点": "邺城",
    "相关人物": [
      "凉茂"
    ],
    "原文": "魏国初建，迁尚书仆射，后为中尉奉常。",
    "事件翻译": "魏国初建时，凉茂升任尚书仆射，后来担任中尉奉常。",
    "std_start_year": 213,
    "涉及的集团": [
      "qiao_jun_cao_xiahou"
    ],
    "所属事件": [
      "caocao_wei_gong_213"
    ],
    "地理信息": [
      "冀州:魏郡:邺县"
    ],
    "是否本传": true
  },
  {
    "事件标题": "凉茂任太子太傅",
    "时间": "建安年间",
    "地点": "邺城",
    "相关人物": [
      "凉茂",
      "曹丕"
    ],
    "原文": "文帝在东宫，茂复为太子太傅，甚见敬礼。",
    "事件翻译": "文帝曹丕在东宫时，凉茂又担任太子太傅，很受尊敬礼遇。",
    "std_start_year": 217,
    "涉及的集团": [
      "qiao_jun_cao_xiahou"
    ],
    "所属事件": [],
    "地理信息": [
      "冀州:魏郡:邺县"
    ],
    "是否本传": true
  },
  {
    "事件标题": "凉茂去世",
    "时间": "建安年间",
    "地点": "邺城",
    "相关人物": [
      "凉茂"
    ],
    "原文": "卒官。[英雄记曰：茂名在八友中。]",
    "事件翻译": "凉茂在任上去世。[英雄记说：凉茂的名字列在八友之中。]",
    "std_start_year": 220,
    "涉及的集团": [],
    "所属事件": [],
    "地理信息": [
      "冀州:魏郡:邺县"
    ],
    "是否本传": true
  }
]