[
  {
    "事件标题": "向朗早年师从司马德操并与徐庶等人交好",
    "时间": "约东汉末年",
    "地点": "荆州",
    "相关人物": [
      "向朗",
      "司马德操",
      "徐庶",
      "韩德高",
      "庞统"
    ],
    "原文": "襄阳记曰：朗少师事司马德操，与徐元直、韩德高、庞士元皆亲善。",
    "事件翻译": "向朗年轻时拜司马德操为师，与徐庶、韩德高、庞统都关系亲密友好。",
    "std_start_year": 190,
    "涉及的集团": [
      "jing_zhou"
    ],
    "所属事件": [],
    "地理信息": [
      "荆州"
    ],
    "是否本传": true
  },
  {
    "事件标题": "向朗被刘表任命为临沮长",
    "时间": "约建安年间",
    "地点": "荆州:南阳郡:临沮",
    "相关人物": [
      "向朗",
      "刘表"
    ],
    "原文": "向朗字巨达，襄阳宜城人也。荆州牧刘表以为临沮长。",
    "事件翻译": "向朗，字巨达，是襄阳宜城人。荆州牧刘表任命他为临沮县长。",
    "std_start_year": 200,
    "涉及的集团": [
      "jing_zhou"
    ],
    "所属事件": [],
    "地理信息": [
      "荆州:南阳郡:临沮"
    ],
    "是否本传": true
  },
  {
    "事件标题": "向朗归附刘备并督四县军民事",
    "时间": "建安十四年",
    "地点": "荆州:南郡:秭归县, 荆州:南郡:夷道县, 荆州:南郡:巫县, 荆州:南郡:夷陵县",
    "相关人物": [
      "向朗",
      "刘备"
    ],
    "原文": "表卒，归先主。先主定江南，使朗督秭归、夷道、巫、夷陵四县军民事。",
    "事件翻译": "刘表去世后，向朗归附了先主刘备。刘备平定江南后，派向朗督察秭归、夷道、巫、夷陵四县的军事和民政事务。",
    "std_start_year": 209,
    "涉及的集团": [
      "jing_zhou"
    ],
    "所属事件": [
      "chi_bi_zhi_zhan"
    ],
    "地理信息": [
      "荆州:南郡:秭归县",
      "荆州:南郡:夷道县",
      "荆州:南郡:巫县",
      "荆州:南郡:夷陵县"
    ],
    "是否本传": true
  },
  {
    "事件标题": "向朗历任巴西、牂牁、房陵太守",
    "时间": "建安十九年至章武年间",
    "地点": "益州:巴西郡, 益州:牂牁郡, 荆州:房陵郡",
    "相关人物": [
      "向朗"
    ],
    "原文": "蜀既平，以朗为巴西太守，顷之转任牂牁，又徙房陵。",
    "事件翻译": "蜀地平定后，任命向朗为巴西太守，不久转任牂牁太守，又调任房陵太守。",
    "std_start_year": 214,
    "涉及的集团": [],
    "所属事件": [
      "liu_bei_ru_chuan"
    ],
    "地理信息": [
      "益州:巴西郡",
      "益州:牂牁郡",
      "荆州:房陵郡"
    ],
    "是否本传": true
  },
  {
    "事件标题": "向朗任步兵校尉并代王连领丞相长史",
    "时间": "章武三年至建兴年间",
    "地点": "益州:蜀郡:成都",
    "相关人物": [
      "向朗",
      "刘禅",
      "王连"
    ],
    "原文": "后主践阼，为步兵校尉，代王连领丞相长史。",
    "事件翻译": "后主刘禅即位后，向朗担任步兵校尉，接替王连兼任丞相长史。",
    "std_start_year": 223,
    "涉及的集团": [],
    "所属事件": [
      "baidi_tuogu_223"
    ],
    "地理信息": [
      "益州:蜀郡:成都"
    ],
    "是否本传": true
  },
  {
    "事件标题": "向朗留守成都并随诸葛亮至汉中",
    "时间": "建兴三年至五年",
    "地点": "益州:蜀郡:成都, 益州:汉中郡",
    "相关人物": [
      "向朗",
      "诸葛亮"
    ],
    "原文": "丞相亮南征，朗留统后事。五年，随亮汉中。",
    "事件翻译": "丞相诸葛亮南征时，向朗留下统管后方事务。建兴五年，向朗随诸葛亮到汉中。",
    "std_start_year": 225,
    "涉及的集团": [],
    "所属事件": [
      "zhuge_liang_nan_zheng",
      "zhuge_1st_north"
    ],
    "地理信息": [
      "益州:蜀郡:成都",
      "益州:汉中郡"
    ],
    "是否本传": true
  },
  {
    "事件标题": "向朗因马谡逃亡知情不举被免官",
    "时间": "建兴六年",
    "地点": "益州:汉中郡",
    "相关人物": [
      "向朗",
      "马谡",
      "诸葛亮"
    ],
    "原文": "朗素与马谡善，谡逃亡，朗知情不举，亮恨之，免官还成都。",
    "事件翻译": "向朗一向与马谡交好，马谡逃亡时，向朗知情不举报，诸葛亮怨恨他，免去他的官职让他返回成都。",
    "std_start_year": 228,
    "涉及的集团": [],
    "所属事件": [
      "zhuge_1st_north"
    ],
    "地理信息": [
      "益州:汉中郡"
    ],
    "是否本传": true
  },
  {
    "事件标题": "向朗复职为光禄勋并封侯",
    "时间": "建兴六年至十二年",
    "地点": "益州:蜀郡:成都",
    "相关人物": [
      "向朗",
      "诸葛亮"
    ],
    "原文": "数年，为光禄勋，亮卒后徒左将军，追论旧功，封显明亭侯，位特进。",
    "事件翻译": "几年后，向朗担任光禄勋，诸葛亮去世后改任左将军，追论旧功，封为显明亭侯，位特进。",
    "std_start_year": 234,
    "涉及的集团": [],
    "所属事件": [],
    "地理信息": [
      "益州:蜀郡:成都"
    ],
    "是否本传": true
  },
  {
    "事件标题": "向朗潜心典籍校书积累",
    "时间": "建兴六年至延熙十年",
    "地点": "益州:蜀郡:成都",
    "相关人物": [
      "向朗"
    ],
    "原文": "初，朗少时虽涉猎文学，然不治素检，以吏能见称。自去长史，优游无事垂三十年，乃更潜心典籍，孜孜不倦。年逾八十，犹手自校书，刊定谬误，积聚篇卷，於时最多。开门接宾，诱纳后进，但讲论古义，不干时事，以是见称。上自执政，下及童冠，皆敬重焉。",
    "事件翻译": "当初，向朗年轻时虽然涉猎文学，但不注重操行检点，以吏治才能著称。自从免去长史后，悠闲无事将近三十年，于是更加潜心钻研典籍，孜孜不倦。年过八十，还亲手校订书籍，刊定谬误，积累的篇章卷帙，在当时最多。开门接待宾客，引导接纳后进，只讲论古义，不干预时事，因此被人称道。上自执政大臣，下至少年儿童，都敬重他。",
    "std_start_year": 228,
    "涉及的集团": [],
    "所属事件": [],
    "地理信息": [
      "益州:蜀郡:成都"
    ],
    "是否本传": true
  },
  {
    "事件标题": "向朗去世",
    "时间": "延熙十年",
    "地点": "益州:蜀郡:成都",
    "相关人物": [
      "向朗"
    ],
    "原文": "延熙十年卒。",
    "事件翻译": "延熙十年，向朗去世。",
    "std_start_year": 247,
    "涉及的集团": [],
    "所属事件": [],
    "地理信息": [
      "益州:蜀郡:成都"
    ],
    "是否本传": true
  },
  {
    "事件标题": "向朗遗言戒子",
    "时间": "延熙十年",
    "地点": "益州:蜀郡:成都",
    "相关人物": [
      "向朗",
      "向条"
    ],
    "原文": "襄阳记曰：朗遗言戒子曰：传称师克在和不在众，此言天地和则万物生，君臣和则国家平，九族和则动得所求，静得所安，是以圣人守和，以存以亡也。吾，楚国之小子耳，而早丧所天，为二兄所诱养，使其性行不随禄利以堕。今但贫耳；贫非人患，惟和为贵，汝其勉之！",
    "事件翻译": "向朗留下遗言告诫儿子说：古语说军队取胜在于和睦而不在于人多，这是说天地和谐则万物生长，君臣和谐则国家太平，九族和谐则行动能达成所求，静止能获得安宁，所以圣人坚守和谐，以存身以立世。我不过是楚国的一个小子，早年丧父，被两位兄长抚养教导，使我的品性行为不因禄利而堕落。如今只是贫穷罢了；贫穷不是人的祸患，只有和谐才是宝贵的，你要努力啊！",
    "std_start_year": 247,
    "涉及的集团": [],
    "所属事件": [],
    "地理信息": [
      "益州:蜀郡:成都"
    ],
    "是否本传": true
  },
  {
    "事件标题": "向条继承爵位并任御史中丞",
    "时间": "景耀年间",
    "地点": "益州:蜀郡:成都",
    "相关人物": [
      "向条"
    ],
    "原文": "子条嗣，景耀中为御史中丞。",
    "事件翻译": "儿子向条继承爵位，景耀年间担任御史中丞。",
    "std_start_year": 258,
    "涉及的集团": [],
    "所属事件": [],
    "地理信息": [
      "益州:蜀郡:成都"
    ],
    "是否本传": false
  },
  {
    "事件标题": "向条入晋后任江阳太守、南中军司马",
    "时间": "西晋初年",
    "地点": "益州:江阳郡, 益州:南中",
    "相关人物": [
      "向条"
    ],
    "原文": "襄阳记曰：条字文豹，亦博学多识，入晋为江阳太守、南中军司马。",
    "事件翻译": "向条字文豹，也博学多识，进入晋朝后担任江阳太守、南中军司马。",
    "std_start_year": 265,
    "涉及的集团": [],
    "所属事件": [],
    "地理信息": [
      "益州:江阳郡",
      "益州:南中"
    ],
    "是否本传": false
  },
  {
    "事件标题": "裴松之考证向朗免官至卒年时间",
    "时间": "建兴六年至延熙十年",
    "地点": "不详",
    "相关人物": [
      "向朗"
    ],
    "原文": "臣松之案：朗坐马谡免长史，则建兴六年中也。朗至延熙十年卒，整二十年耳，此云三十，字之误也。",
    "事件翻译": "裴松之考证：向朗因马谡事被免去长史，是在建兴六年。向朗到延熙十年去世，整二十年，这里说三十年，是文字错误。",
    "std_start_year": 228,
    "涉及的集团": [],
    "所属事件": [],
    "地理信息": [],
    "是否本传": true
  },
  {
    "事件标题": "向宠在秭归之战中保全营地",
    "时间": "章武二年",
    "地点": "荆州:南郡:秭归县",
    "相关人物": [
      "向宠",
      "刘备"
    ],
    "原文": "朗兄子宠，先主时为牙门将。秭归之败，宠营特完。",
    "事件翻译": "向朗哥哥的儿子向宠，在刘备担任先主时担任牙门将。在秭归战败时，向宠的军营独自完好无损。",
    "std_start_year": 222,
    "涉及的集团": [
      "jing_zhou"
    ],
    "所属事件": [
      "yi_ling_zhi_zhan"
    ],
    "地理信息": [
      "荆州:南郡:秭归县"
    ],
    "是否本传": false
  },
  {
    "事件标题": "向宠被封为都亭侯并担任中部督",
    "时间": "建兴元年",
    "地点": "益州:蜀郡:成都",
    "相关人物": [
      "向宠",
      "刘禅"
    ],
    "原文": "建兴元年封都亭侯，后为中部督，典宿卫兵。",
    "事件翻译": "建兴元年，向宠被封为都亭侯，后来担任中部督，掌管宫廷宿卫士兵。",
    "std_start_year": 223,
    "涉及的集团": [
      "jing_zhou"
    ],
    "所属事件": [],
    "地理信息": [
      "益州:蜀郡:成都"
    ],
    "是否本传": false
  },
  {
    "事件标题": "诸葛亮上表推荐向宠",
    "时间": "建兴五年",
    "地点": "益州:蜀郡:成都",
    "相关人物": [
      "诸葛亮",
      "向宠",
      "刘禅",
      "刘备"
    ],
    "原文": "诸葛亮当北行，表与后主曰：将军向宠，性行淑均，晓畅军事，试用於昔，先帝称之曰能，是以众论举宠为督。愚以为营中之事，悉以咨之，必能使行陈和睦，优劣得所也。",
    "事件翻译": "诸葛亮即将北伐时，上表给后主刘禅说：将军向宠，品性善良公正，通晓军事，过去曾试用过，先帝称赞他有才能，所以众人议论推举向宠为中部督。我认为军营中的事务，都向他咨询，一定能使军队和睦，优劣各得其所。",
    "std_start_year": 227,
    "涉及的集团": [
      "jing_zhou"
    ],
    "所属事件": [
      "zhuge_1st_north"
    ],
    "地理信息": [
      "益州:蜀郡:成都"
    ],
    "是否本传": false
  },
  {
    "事件标题": "向宠升任中领军",
    "时间": "建兴五年后",
    "地点": "益州:蜀郡:成都",
    "相关人物": [
      "向宠"
    ],
    "原文": "迁中领军。",
    "事件翻译": "向宠升任中领军。",
    "std_start_year": 228,
    "涉及的集团": [
      "jing_zhou"
    ],
    "所属事件": [],
    "地理信息": [
      "益州:蜀郡:成都"
    ],
    "是否本传": false
  },
  {
    "事件标题": "向宠征讨汉嘉蛮夷时遇害",
    "时间": "延熙三年",
    "地点": "益州:蜀郡",
    "相关人物": [
      "向宠"
    ],
    "原文": "延熙三年，征汉嘉蛮夷，遇害。",
    "事件翻译": "延熙三年，向宠征讨汉嘉的蛮夷，遇害身亡。",
    "std_start_year": 240,
    "涉及的集团": [
      "jing_zhou"
    ],
    "所属事件": [],
    "地理信息": [
      "益州:蜀郡"
    ],
    "是否本传": false
  },
  {
    "事件标题": "向充历任射声校尉尚书",
    "时间": "不详",
    "地点": "益州:蜀郡:成都",
    "相关人物": [
      "向充"
    ],
    "原文": "宠弟充，历射声校尉尚书。",
    "事件翻译": "向宠的弟弟向充，历任射声校尉和尚书。",
    "std_start_year": null,
    "涉及的集团": [
      "jing_zhou"
    ],
    "所属事件": [],
    "地理信息": [
      "益州:蜀郡:成都"
    ],
    "是否本传": false
  },
  {
    "事件标题": "卫瓘在成都获得玉印",
    "时间": "魏咸熙元年六月",
    "地点": "益州:蜀郡:成都",
    "相关人物": [
      "卫瓘",
      "向充",
      "谯周",
      "刘备",
      "刘禅",
      "司马炎"
    ],
    "原文": "襄阳记曰：魏咸熙元年六月，镇西将军卫瓘至於成都，得璧玉印一枚，文似成信字，魏人宣示百官，藏于相国府。充闻之曰：吾闻谯周之言，先帝讳备，其训具也，后主讳禅，其训授也，如言刘已具矣，当授与人也。今中抚军名炎，而汉年极於炎兴，瑞出成都，而藏之於相国府，此殆天意也。是岁，拜充为梓潼太守，明年十二月而晋武帝即尊位，炎兴於是乎徵焉。孙盛曰：昔公孙自以起成都，号曰成氏，二玉之文，殆述所作乎！",
    "事件翻译": "《襄阳记》记载：魏咸熙元年六月，镇西将军卫瓘到达成都，得到一枚璧玉印，上面的文字像是“成信”二字，魏人向百官展示，收藏在相国府。向充听说后说：我听说谯周的话，先帝名备，意思是“具”，后主名禅，意思是“授”，就像说刘氏已经完备了，应当授予他人。现在中抚军名炎，而汉朝的年号结束于炎兴，祥瑞出现在成都，却收藏在相国府，这大概是天意吧。这一年，朝廷任命向充为梓潼太守，第二年十二月晋武帝即位，炎兴的年号于是应验了。孙盛说：过去公孙述自认为兴起于成都，号称成氏，这两个玉印的文字，恐怕是公孙述所作的吧！",
    "std_start_year": 264,
    "涉及的集团": [
      "jing_zhou"
    ],
    "所属事件": [
      "wei_mie_shu"
    ],
    "地理信息": [
      "益州:蜀郡:成都"
    ],
    "是否本传": false
  },
  {
    "事件标题": "补充遗漏文本",
    "时间": "不详",
    "地点": "不详",
    "相关人物": [],
    "原文": "[襄阳记曰：魏咸熙元年六月，镇西将军卫瓘至於成都，得璧玉印各一枚，文似成信字，魏人宣示百官，藏于相国府。充闻之曰：吾闻谯周之言，先帝讳备，其训具也，后主讳禅，其训授也，如言刘已具矣，当授与人也。今中抚军名炎，而汉年极於炎兴，瑞出成都，而藏之於相国府，此殆天意也。是岁，拜充为梓潼太守，明年十二月而晋武帝即尊位，炎兴於是乎徵焉。孙盛曰：昔公孙自以起成都，号曰成氏，二玉之文，殆述所作乎！]",
    "事件翻译": "[襄阳记曰：魏咸熙元年六月，镇西将军卫瓘至於成都，得璧玉印各一枚，文似成信字，魏人宣示百官，藏于相国府。充闻之曰：吾闻谯周之言，先帝讳备，其训具也，后主讳禅，其训授也，如言刘已具矣，当授与人也。今中抚军名炎，而汉年极於炎兴，瑞出成都，而藏之於相国府，此殆天意也。是岁，拜充为梓潼太守，明年十二月而晋武帝即尊位，炎兴於是乎徵焉。孙盛曰：昔公孙自以起成都，号曰成氏，二玉之文，殆述所作乎！]",
    "std_start_year": null,
    "涉及的集团": [],
    "所属事件": [],
    "地理信息": [],
    "是否本传": false
  }
]