[
  {
    "事件标题": "随孙策征战，初显忠诚",
    "时间": "不详",
    "地点": "不详",
    "相关人物": [
      "周泰",
      "孙策",
      "蒋钦"
    ],
    "事件简介": "周泰与蒋钦一同跟随孙策，作为左右近侍，恭敬服侍，多次作战有功。孙策进入会稽后，任命周泰为别部司马，并授予兵权。",
    "事件类型": "军事征伐",
    "影响/结果": "周泰获得孙策信任，开始统领军队，为日后成为孙权心腹奠定基础。",
    "原文": "周泰字幼平，九江下蔡人也。与蒋钦随孙策为左右，服事恭敬，数战有功。策入会稽，署别部司马，授兵。",
    "std_start_year": null,
    "std_end_year": null,
    "is_time_fuzzy": true
  },
  {
    "事件标题": "宣城救孙权，身受重伤",
    "时间": "不详",
    "地点": "宣城",
    "相关人物": [
      "周泰",
      "孙权",
      "孙策"
    ],
    "事件简介": "孙策讨伐六县山贼时，孙权驻守宣城，兵力不足千人且防备松懈。数千山贼突然杀到，孙权刚上马，贼兵已逼近，甚至砍中马鞍。众人惊慌失措，只有周泰奋勇护卫孙权，胆气倍增，激励左右一同作战。贼兵退散后，周泰身中十二处创伤，很久才苏醒。如果没有周泰，孙权几乎遇险。孙策因此深深感激周泰，任命他为春谷县长。",
    "事件类型": "军事征伐",
    "影响/结果": "周泰舍命救孙权，成为孙权最信任的将领之一，奠定了他在东吴军中的特殊地位。",
    "原文": "权爱其为人，请以自给。策讨六县山贼，权住宣城，使士自卫，不能千人，意尚忽略，不治围落，而山贼数千人卒至。权始得上马，而贼锋刃已交於左右，或斫中马鞍，众莫能自定。惟泰奋激，投身卫权，胆气倍人，左右由泰并能就战。贼既解散，身被十二创，良久乃苏。是日无泰，权几危殆。策深德之，补春谷长。",
    "std_start_year": null,
    "std_end_year": null,
    "is_time_fuzzy": true
  },
  {
    "事件标题": "随征皖、江夏等地",
    "时间": "不详",
    "地点": "皖、江夏、豫章",
    "相关人物": [
      "周泰",
      "孙权"
    ],
    "事件简介": "周泰随军攻打皖城，又讨伐江夏，回师经过豫章，再次被任命为宜春县长。他在任职的地方都能征收赋税。",
    "事件类型": "军事征伐",
    "影响/结果": "周泰在多次征战中积累军功，并担任地方长官，进一步巩固了其地位。",
    "原文": "后从攻皖，及讨江夏，还过豫章，复补宜春长，所在皆食其征赋。",
    "std_start_year": null,
    "std_end_year": null,
    "is_time_fuzzy": true
  },
  {
    "事件标题": "赤壁、南郡之战",
    "时间": "建安十三年（208年）",
    "地点": "赤壁、南郡",
    "相关人物": [
      "周泰",
      "周瑜",
      "程普",
      "曹操",
      "曹仁"
    ],
    "事件简介": "周泰跟随周瑜、程普在赤壁抵御曹操，随后又参与攻打南郡的曹仁。荆州平定后，周泰率兵驻扎在岑地。",
    "事件类型": "军事征伐",
    "影响/结果": "周泰参与了决定天下大势的关键战役，为东吴赢得赤壁之战和巩固荆州做出了贡献。",
    "原文": "后与周瑜、程普拒曹公於赤壁，攻曹仁於南郡。荆州平定，将兵屯岑。",
    "std_start_year": 208,
    "std_end_year": 208,
    "is_time_fuzzy": false
  },
  {
    "事件标题": "濡须督军，解衣示创",
    "时间": "不详",
    "地点": "濡须",
    "相关人物": [
      "周泰",
      "孙权",
      "朱然",
      "徐盛"
    ],
    "事件简介": "曹操出兵濡须，周泰率军迎击，曹操退兵后，周泰被留下督管濡须，并被任命为平虏将军。当时朱然、徐盛等都在周泰部下，心中不服。孙权特意到濡须坞巡视，大宴诸将。孙权亲自到周泰面前，让他解开衣服，用手指着他身上的伤疤询问来历。周泰一一回忆战斗地点作答。之后孙权让他穿上衣服，欢宴至深夜。第二天，孙权又派使者授予周泰御用伞盖。朱然、徐盛等这才心服。",
    "事件类型": "军事征伐",
    "影响/结果": "孙权通过当众展示周泰的伤疤，彰显其功绩，平息了部将的不满，巩固了周泰的统帅地位。",
    "原文": "曹公出濡须，泰复赴击，曹公退，留督濡须，拜平虏将军。时朱然、徐盛等皆在所部，并不伏也，权特为案行至濡须坞，因会诸将，大为酣乐。权自行酒到泰前，命泰解衣，权手自指其创痕，问以所起。泰辄记昔战斗处以对，毕，使复服，欢宴极夜。其明日，遣使者授以御盖。",
    "std_start_year": null,
    "std_end_year": null,
    "is_time_fuzzy": true
  },
  {
    "事件标题": "受封汉中太守、奋威将军",
    "时间": "不详",
    "地点": "不详",
    "相关人物": [
      "周泰",
      "孙权",
      "关羽"
    ],
    "事件简介": "孙权击败关羽后，计划进一步图谋蜀地，于是任命周泰为汉中太守、奋威将军，并封为陵阳侯。",
    "事件类型": "政治谋略",
    "影响/结果": "周泰获得高位封赏，成为东吴的重要将领，但汉中并未实际控制，此任命更多是象征性的激励。",
    "原文": "后权破关羽，欲进图蜀，拜泰汉中太守、奋威将军，封陵阳侯。",
    "std_start_year": null,
    "std_end_year": null,
    "is_time_fuzzy": true
  },
  {
    "事件标题": "黄武年间去世",
    "时间": "黄武年间（222年-229年）",
    "地点": "不详",
    "相关人物": [
      "周泰"
    ],
    "事件简介": "周泰在黄武年间去世。他的儿子周邵以骑都尉身份统领军队，后来战死。弟弟周承继承爵位并领兵。",
    "事件类型": "内政治理",
    "影响/结果": "周泰去世，其家族继续为东吴效力。",
    "原文": "黄武中卒。子邵以骑都尉领兵。曹仁出濡须，战有功，又从攻破曹休，进位裨将军，黄龙二年卒。弟承领兵袭侯。",
    "std_start_year": 222,
    "std_end_year": 229,
    "is_time_fuzzy": true
  }
]