[
  {
    "事件标题": "初任护军校尉",
    "时间": "不详",
    "地点": "不详",
    "相关人物": [
      "孙皎"
    ],
    "事件简介": "孙皎最初被任命为护军校尉，统领两千多士兵。",
    "事件类型": "军事征伐",
    "影响/结果": "孙皎开始掌握兵权，为后续军事活动奠定基础。",
    "原文": "孙皎字叔朗，始拜护军校尉，领众二千馀人。",
    "std_start_year": null,
    "std_end_year": null,
    "is_time_fuzzy": true
  },
  {
    "事件标题": "抵御曹操于濡须",
    "时间": "不详",
    "地点": "濡须",
    "相关人物": [
      "孙皎",
      "曹操"
    ],
    "事件简介": "曹操多次出兵濡须，孙皎每次都率军抵御，其部队被称为精锐。",
    "事件类型": "军事征伐",
    "影响/结果": "孙皎因作战勇猛，部队获精锐称号，提升了声望。",
    "原文": "是时曹公数出濡须，皎每赴拒，号为精锐。",
    "std_start_year": null,
    "std_end_year": null,
    "is_time_fuzzy": true
  },
  {
    "事件标题": "迁都护征虏将军督夏口",
    "时间": "不详",
    "地点": "夏口",
    "相关人物": [
      "孙皎",
      "程普",
      "黄盖",
      "孙瑜"
    ],
    "事件简介": "孙皎升任都护征虏将军，接替程普督管夏口。黄盖和兄长孙瑜去世后，他又合并了他们的军队。",
    "事件类型": "军事征伐",
    "影响/结果": "孙皎的军权进一步扩大，成为镇守夏口的重要将领。",
    "原文": "迁都护征虏将军，代程普督夏口。黄盖及兄瑜卒，又并其军。",
    "std_start_year": null,
    "std_end_year": null,
    "is_time_fuzzy": true
  },
  {
    "事件标题": "获赐奉邑并自置长吏",
    "时间": "不详",
    "地点": "沙羡、云杜、南新市、竟陵",
    "相关人物": [
      "孙皎"
    ],
    "事件简介": "孙皎被赐予沙羡、云杜、南新市、竟陵四县作为奉邑，并允许自行任命官吏。",
    "事件类型": "政治谋略",
    "影响/结果": "孙皎获得了地方行政权力，增强了其经济和政治实力。",
    "原文": "赐沙羡、云杜、南新市、竟陵为奉邑，自置长吏。",
    "std_start_year": null,
    "std_end_year": null,
    "is_time_fuzzy": true
  },
  {
    "事件标题": "轻财好施善交结",
    "时间": "不详",
    "地点": "不详",
    "相关人物": [
      "孙皎",
      "诸葛瑾",
      "刘靖",
      "李允",
      "吴硕",
      "张梁"
    ],
    "事件简介": "孙皎轻视财物，乐于施舍，善于结交。他与诸葛瑾关系深厚，并委任刘靖、李允、吴硕、张梁等人分别处理得失、众事和军旅事务，对他们倾心相待，这些人也都尽心尽力。",
    "事件类型": "政治谋略",
    "影响/结果": "孙皎通过礼贤下士和合理用人，赢得了部下的忠诚，巩固了其统治基础。",
    "原文": "轻财能施，善於交结，与诸葛瑾至厚，委庐江刘靖以得失，江夏李允以众事，广陵吴硕、河南张梁以军旅，而倾心亲待，莫不自尽。",
    "std_start_year": null,
    "std_end_year": null,
    "is_time_fuzzy": true
  },
  {
    "事件标题": "释放魏边将吏美女",
    "时间": "不详",
    "地点": "江淮间",
    "相关人物": [
      "孙皎"
    ],
    "事件简介": "孙皎曾派兵侦察，抓获了魏国边境将领和官吏的美女，但他为她们更换衣服后送还，并下令说：'现在要诛杀的是曹氏，百姓有什么罪？从今以后，不得攻击老弱百姓。'",
    "事件类型": "政治谋略",
    "影响/结果": "此举赢得了江淮间百姓的归附，提升了孙皎的声望。",
    "原文": "皎尝遣兵候获魏边将吏美女以进皎，皎更其衣服送还之，下令曰：'今所诛者曹氏，其百姓何罪？自今以往，不得击其老弱。'由是江淮间多归附者。",
    "std_start_year": null,
    "std_end_year": null,
    "is_time_fuzzy": true
  },
  {
    "事件标题": "与甘宁忿争及孙权劝和",
    "时间": "不详",
    "地点": "不详",
    "相关人物": [
      "孙皎",
      "甘宁",
      "孙权",
      "诸葛瑾"
    ],
    "事件简介": "孙皎曾因小事与甘宁发生激烈争执。有人劝甘宁，甘宁表示自己只愿效忠明主，不能屈从。孙权听说后，写信责备孙皎，指出他作为重臣不应因私怨而欺凌他人，并派诸葛瑾传达旨意。孙皎收到信后上疏认错，于是与甘宁结为厚交。",
    "事件类型": "内政治理",
    "影响/结果": "孙皎在孙权调解下与甘宁和解，避免了内部冲突的扩大，维护了军队团结。",
    "原文": "尝以小故与甘宁忿争，或以谏宁，宁曰：'臣子一例，征虏虽公子，何可专行侮人邪！吾值明主，但当输效力命，以报所天，诚不能随俗屈曲矣。'权闻之，以书让皎曰：'自吾与北方为敌，中间十年，初时相持年小，今者且三十矣。孔子言'三十而立'，非但谓五经也。授卿以精兵，委卿以大任，都护诸将於千里之外，欲使如楚任昭奚恤，扬威於北境，非徒相使逞私志而已。近闻卿与甘兴霸饮，因酒发作，侵陵其人，其人求属吕蒙督中。此人虽粗豪，有不如人意时，然其较略大丈夫也。吾亲之者，非私之也。我亲爱之，卿疏憎之；卿所为每与吾违，其可久乎？夫居敬而行简，可以临民；爱人多容，可以得众。二者尚不能知，安可董督在远，御寇济难乎？卿行长大，特受重任，上有远方瞻望之视，下有部曲朝夕从事，何可恣意有盛怒邪？人谁无过，贵其能改，宜追前愆，深自咎责。今故烦诸葛子瑜重宣吾意。临书摧怆，心悲泪下。'皎得书，上疏陈谢，遂与宁结厚。",
    "std_start_year": null,
    "std_end_year": null,
    "is_time_fuzzy": true
  },
  {
    "事件标题": "参与袭取南郡和荆州之战",
    "时间": "建安二十四年（219年）",
    "地点": "南郡、荆州",
    "相关人物": [
      "孙皎",
      "吕蒙",
      "孙权",
      "关羽"
    ],
    "事件简介": "吕蒙准备袭击南郡时，孙权想任命孙皎和吕蒙为左右部大督。吕蒙以周瑜、程普不睦的前车之鉴劝说孙权，孙权醒悟，改任吕蒙为大督，孙皎为后继。最终擒获关羽、平定荆州，孙皎在其中立下功劳。",
    "事件类型": "军事征伐",
    "影响/结果": "孙皎在荆州之战中发挥了重要作用，协助吕蒙成功夺取荆州，擒杀关羽。",
    "原文": "后吕蒙当袭南郡，权欲令皎与蒙为左右部大督，蒙说权曰：'若至尊以征虏能，宜用之；以蒙能，宜用蒙。昔周瑜、程普为左右部督，共攻江陵，虽事决於瑜，普自恃久将，且俱是督，遂共不睦，几败国事，此目前之戒也。'权寤，谢蒙曰：'以卿为大督，命皎为后继。'禽关羽，定荆州，皎有力焉。",
    "std_start_year": 219,
    "std_end_year": 219,
    "is_time_fuzzy": false
  },
  {
    "事件标题": "去世及追封",
    "时间": "建安二十四年（219年）",
    "地点": "不详",
    "相关人物": [
      "孙皎",
      "孙权",
      "孙胤"
    ],
    "事件简介": "孙皎在建安二十四年去世。孙权追录他的功劳，封其子孙胤为丹杨侯。孙胤去世后无子，由弟弟孙晞继承，后因罪自杀，封国被废除。",
    "事件类型": "政治谋略",
    "影响/结果": "孙皎去世后，其家族爵位短暂传承后因罪被废，但其子孙仍有数人担任将军并封侯。",
    "原文": "建安二十四年卒。权追录其功，封子胤为丹杨侯。胤卒，无子。弟晞嗣，领兵，有罪自杀，国除。弟咨、弥、仪皆将军，封侯。咨羽林督，仪无难督。咨为滕胤所杀，仪为孙峻所害。",
    "std_start_year": 219,
    "std_end_year": 219,
    "is_time_fuzzy": false
  }
]