[
  {
    "事件标题": "孙皓被立为吴国皇帝",
    "时间": "咸熙元年",
    "地点": "吴国",
    "相关人物": [
      "孙皓",
      "孙休",
      "景养",
      "万彧",
      "濮阳兴",
      "张布",
      "朱太后"
    ],
    "原文": "孙皓字元宗，权孙，和子也，一名彭祖，字皓宗。孙休立，封皓为乌程侯，遣就国。西湖民景养相皓当大贵，皓阴喜而不敢泄。休薨，是时蜀初亡，而交阯携叛，国内震惧，贪得长君。左典军万彧昔为乌程令，与皓相善，称皓才识明断，是长沙桓王之畴也，又加之好学，奉遵法度，屡言之於丞相濮阳兴、左将军张布。兴、布说休妃太后朱，欲以皓为嗣。朱曰：我寡妇人，安知社稷之虑，苟吴国无损，宗庙有赖可矣。於是遂迎立皓，时年二十三。改元，大赦。是岁，於魏咸熙元年也。",
    "事件翻译": "孙皓字元宗，是孙权的孙子，孙和的儿子，又名彭祖，字皓宗。孙休即位后，封孙皓为乌程侯，让他前往封国。西湖有个百姓叫景养，给孙皓看相，说他将来会大富大贵，孙皓暗中高兴但不敢泄露。孙休去世时，蜀汉刚刚灭亡，交阯又发生叛乱，吴国上下震惊恐惧，希望有一位年长的君主。左典军万彧从前担任乌程县令，与孙皓关系很好，称赞孙皓才智明断，是长沙桓王孙策一类的人物，再加上他好学，遵守法度，多次向丞相濮阳兴、左将军张布进言。濮阳兴、张布劝说孙休的妃子朱太后，想立孙皓为继承人。朱太后说：我是一个寡妇，哪里懂得国家大事，只要吴国没有损害，宗庙有所依赖就可以了。于是迎立孙皓，当时他二十三岁。改年号，大赦天下。这一年，是魏国的咸熙元年。",
    "std_start_year": 264,
    "涉及的集团": [
      "jiang_dong"
    ],
    "所属事件": [],
    "地理信息": [
      "扬州:吴郡:乌程"
    ],
    "是否本传": true
  },
  {
    "事件标题": "孙皓即位后调整官职与封赏",
    "时间": "元兴元年八月",
    "地点": "吴国都城",
    "相关人物": [
      "孙皓",
      "施绩",
      "丁奉",
      "张布"
    ],
    "原文": "元兴元年八月，以上大将军施绩、大将军丁奉为左右大司马，张布为骠骑将军，加侍中，诸增位班赏，一皆如旧。",
    "事件翻译": "元兴元年八月，孙皓任命上大将军施绩、大将军丁奉为左右大司马，张布为骠骑将军，加授侍中，其他增加官位和赏赐，一律按照旧例。",
    "std_start_year": 264,
    "涉及的集团": [
      "jiang_dong"
    ],
    "所属事件": [],
    "地理信息": [
      "扬州:吴郡:吴县"
    ],
    "是否本传": true
  },
  {
    "事件标题": "孙皓贬太后、追谥父、尊母、封诸王及立后",
    "时间": "元兴元年九月至十月",
    "地点": "吴国都城",
    "相关人物": [
      "孙皓",
      "太后朱氏",
      "孙和",
      "何氏",
      "孙休太子孙𩅦",
      "滕氏"
    ],
    "原文": "九月，贬太后为景皇后，追谥父和曰文皇帝，尊母何为太后。十月，封休太子｛雨單｝为豫章王，次子汝南王，次子梁王，次子陈王，立皇后滕氏。",
    "事件翻译": "九月，孙皓将太后朱氏贬为景皇后，追谥父亲孙和为文皇帝，尊母亲何氏为太后。十月，封孙休的太子孙𩅦为豫章王，次子为汝南王，三子为梁王，四子为陈王，立滕氏为皇后。",
    "std_start_year": 264,
    "涉及的集团": [
      "jiang_dong"
    ],
    "所属事件": [],
    "地理信息": [
      "扬州:吴郡:吴县"
    ],
    "是否本传": true
  },
  {
    "事件标题": "孙皓初立时施仁政的记载",
    "时间": "元兴元年",
    "地点": "吴国",
    "相关人物": [
      "孙皓"
    ],
    "原文": "[江表传曰：皓初立，发优诏，恤士民，开仓禀，振贫乏，科出宫女以配无妻，禽兽扰於苑者皆放之。当时翕然称为明主。]",
    "事件翻译": "《江表传》记载：孙皓刚即位时，发布优待诏书，抚恤士民，打开粮仓，赈济贫困，放出宫女配给没有妻子的人，苑囿中扰民的禽兽都放掉。当时一致称颂他为明主。",
    "std_start_year": 264,
    "涉及的集团": [
      "jiang_dong"
    ],
    "所属事件": [],
    "地理信息": [
      "扬州:吴郡:吴县"
    ],
    "是否本传": true
  },
  {
    "事件标题": "孙皓诛杀濮阳兴和张布",
    "时间": "元兴元年十一月",
    "地点": "吴国都城",
    "相关人物": [
      "孙皓",
      "濮阳兴",
      "张布"
    ],
    "原文": "皓既得志，粗暴骄盈，多忌讳，好酒色，大小失望。兴、布窃悔之。或以谮皓，十一月，诛兴、布。",
    "事件翻译": "孙皓得志后，变得粗暴骄盈，多忌讳，好酒色，大小官员都失望。濮阳兴、张布私下后悔立他。有人向孙皓进谗言，十一月，孙皓诛杀了濮阳兴和张布。",
    "std_start_year": 264,
    "涉及的集团": [
      "jiang_dong"
    ],
    "所属事件": [],
    "地理信息": [
      "扬州:吴郡:吴县"
    ],
    "是否本传": true
  },
  {
    "事件标题": "孙休下葬及孙皓封赏外戚",
    "时间": "元兴元年十二月",
    "地点": "定陵",
    "相关人物": [
      "孙皓",
      "孙休",
      "滕牧",
      "何洪"
    ],
    "原文": "十二月，孙休葬定陵。封后父滕牧为高密侯，[吴历曰：牧本名密，避丁密，改名牧，丁密避牧，改名为固。]舅何洪等三人皆列侯。",
    "事件翻译": "十二月，孙休被安葬在定陵。孙皓封皇后之父滕牧为高密侯，舅舅何洪等三人都封为列侯。",
    "std_start_year": 264,
    "涉及的集团": [
      "jiang_dong"
    ],
    "所属事件": [],
    "地理信息": [
      "扬州:吴郡:乌程县"
    ],
    "是否本传": true
  },
  {
    "事件标题": "魏国派遣交阯太守及晋王致书孙皓",
    "时间": "元兴元年",
    "地点": "魏国、吴国",
    "相关人物": [
      "孙皓",
      "徐绍",
      "孙彧",
      "司马昭"
    ],
    "原文": "是岁，魏置交阯太守之郡。晋文帝为魏相国，遣昔吴寿春城降将徐绍、孙彧衔命赍书，陈事势利害，以申喻皓。[汉晋春秋载晋文王与皓书曰：圣人称有君臣然后有上下礼义，是故大必字小，小必事大，然后上下安服，群生获所。逮至末涂，纯德既毁，剿民之命，以争强於天下，违礼顺之至理，则仁者弗由也。方今主上圣明，覆帱无外，仆备位宰辅，属当国重。唯华夏乖殊，方隅圮裂，六十馀载，金革亟动，无年不战，暴骸丧元，困悴罔定，每用悼心，坐以待旦。将欲止戈兴仁，为百姓请命，故分命偏师，平定蜀汉，役未经年，全军独克。于时猛将谋夫，朝臣庶士，咸以奉天时之宜，就既征之军，藉吞敌之势，宜遂回旗东指，以临吴境。舟师泛江，顺流而下，陆军南辕，取径四郡，兼成都之械，漕巴汉之粟，然后以中军整旅，三方云会，未及浃辰，可使江表厎平，南夏顺轨。然国朝深惟伐蜀之举，虽有静难之功，亦悼蜀民独罹其害，战於绵竹者，自元帅以下并受斩戮，伏尸蔽地，血流丹野。一之於前，犹追恨不忍，况重之於后乎？是故旋师按甲，思与南邦共全百姓之命。夫料力忖势，度资量险，远考古昔废兴之理，近鉴西蜀安危之效，隆德保祚，去危即顺，屈己以宁四海者，仁哲之高致也；履危偷安，陨德覆祚，而不称於后世者，非智者之所居也。今朝廷遣徐绍、孙彧献书喻怀，若书御於前，必少留意，回虑革算，结欢弭兵，共为一家，惠矜吴会，施及中土，岂不泰哉！此昭心之大愿也，敢不承受。若不获命，则普天率土，期於大同，虽重干戈，固不获已也。]",
    "事件翻译": "这一年，魏国设置交阯太守到郡上任。晋文王司马昭担任魏国相国，派遣从前在吴国寿春城投降的将领徐绍、孙彧带着书信，陈述事势利害，来开导孙皓。",
    "std_start_year": 264,
    "涉及的集团": [
      "he_nei_sima"
    ],
    "所属事件": [],
    "地理信息": [
      "交州:交阯郡"
    ],
    "是否本传": true
  },
  {
    "事件标题": "孙皓遣使报书晋文帝",
    "时间": "甘露元年三月",
    "地点": "建业",
    "相关人物": [
      "孙皓",
      "徐绍",
      "孙彧",
      "纪陟",
      "弘璆"
    ],
    "原文": "甘露元年三月，皓遣使随绍、彧报书曰：知以高世之才，处宰辅之任，渐导之功，勤亦至矣。孤以不德，阶承统绪，思与贤良共济世道，而以壅隔未有所缘，嘉意允著，深用依依。今遣光禄大夫纪陟、五官中郎将弘璆宣明至怀。[江表传曰：皓书两头言白，称名言而不著姓。吴录曰：陟字子上，丹杨人。初为中书郎，孙峻使诘南阳王和，令其引分。陟密使令正辞自理，峻怒。陟惧，闭门不出。孙休时，父亮为尚书令，而陟为中书令，每朝会，诏以屏风隔其座。出为豫章太守。干宝晋纪曰：陟、璆奉使如魏，入境而问讳，入国而问俗。寿春将王布示之马射，既而问之曰：吴之君子亦能斯乎？陟曰：此军人骑士肄业所及，士大夫君子未有为之者矣。布大惭。既至，魏帝见之，使儐问曰：来时吴王何如？陟对曰：来时皇帝临轩，百寮陪位，御膳无恙。晋文王飨之，百寮毕会，使儐者告曰：某者安乐公也，某者匈奴单于也。陟曰：西主失土，为君王所礼，位同三代，莫不感义，匈奴边塞难羁之国，君王怀之，亲在坐席，此诚威恩远著。又问：吴之戍备几何？对曰：自西陵以至江都，五千七百里。又问曰：道里甚远，难为坚固？对曰：疆界虽远，而其险要必争之地，不过数四，犹人虽有八尺之躯靡不受患，其护风寒亦数处耳。文王善之，厚为之礼。臣松之以为人有八尺之体靡不受患，防护风寒岂唯数处？取譬若此，未足称能。若曰譬如金城万雉，所急防者四门而已。方陟此对，不犹愈乎！吴录曰：皓以诸父与和相连及者，家属皆徙东冶，唯陟以有密旨，特封子孚都亭侯。孚弟瞻，字思远，入仕晋骠骑将军。弘璆，曲阿人，弘咨之孙，权外甥也。璆后至中书令、太子少傅。]",
    "事件翻译": "甘露元年三月，孙皓派遣使者跟随徐绍、孙彧回信说：知道您以高世之才，担任宰辅之任，引导劝化的功劳，也到了极点。我以无德之身，继承大统，想与贤良共同治理世道，但因阻隔未能有机会，您的善意显著，我深感依恋。现在派遣光禄大夫纪陟、五官中郎将弘璆宣明我的至诚之心。",
    "std_start_year": 265,
    "涉及的集团": [
      "jiang_dong"
    ],
    "所属事件": [],
    "地理信息": [
      "扬州:丹杨郡:建业县"
    ],
    "是否本传": true
  },
  {
    "事件标题": "孙皓召回并杀死徐绍",
    "时间": "甘露元年",
    "地点": "濡须",
    "相关人物": [
      "孙皓",
      "徐绍"
    ],
    "原文": "绍行到濡须，召还杀之，徙其家属建安，始有白绍称美中国者故也。",
    "事件翻译": "徐绍走到濡须，孙皓将他召回并杀死，将其家属流放到建安，这是因为有人告发徐绍称赞中原的缘故。",
    "std_start_year": 265,
    "涉及的集团": [
      "jiang_dong"
    ],
    "所属事件": [],
    "地理信息": [
      "扬州:九江郡:濡须"
    ],
    "是否本传": true
  },
  {
    "事件标题": "孙皓改元大赦",
    "时间": "甘露元年夏四月",
    "地点": "建业",
    "相关人物": [
      "孙皓"
    ],
    "原文": "夏四月，蒋陵言甘露降，於是改年大赦。",
    "事件翻译": "夏季四月，蒋陵报告说降下甘露，于是改年号并大赦天下。",
    "std_start_year": 265,
    "涉及的集团": [
      "jiang_dong"
    ],
    "所属事件": [],
    "地理信息": [
      "扬州:丹杨郡:建业县"
    ],
    "是否本传": true
  },
  {
    "事件标题": "孙皓逼杀景后朱氏",
    "时间": "甘露元年秋七月",
    "地点": "建业",
    "相关人物": [
      "孙皓",
      "景后朱氏"
    ],
    "原文": "秋七月，皓逼杀景后朱氏，亡不在正殿，於苑中小屋治丧，众知其非疾病，莫不痛切。",
    "事件翻译": "秋季七月，孙皓逼迫杀死景后朱氏，死后不在正殿停灵，在苑中的小屋里治丧，众人知道她不是因病而死，无不悲痛。",
    "std_start_year": 265,
    "涉及的集团": [
      "jiang_dong"
    ],
    "所属事件": [],
    "地理信息": [
      "扬州:丹杨郡:建业县"
    ],
    "是否本传": true
  },
  {
    "事件标题": "孙皓追杀孙休诸子",
    "时间": "甘露元年秋七月",
    "地点": "吴小城",
    "相关人物": [
      "孙皓",
      "孙休"
    ],
    "原文": "又送休四子於吴小城，寻复追杀大者二人。",
    "事件翻译": "又将孙休的四个儿子送到吴小城，不久又追杀了其中年长的两个。",
    "std_start_year": 265,
    "涉及的集团": [
      "jiang_dong"
    ],
    "所属事件": [],
    "地理信息": [
      "扬州:吴郡:吴县"
    ],
    "是否本传": true
  },
  {
    "事件标题": "孙皓迁都武昌",
    "时间": "甘露元年九月",
    "地点": "武昌",
    "相关人物": [
      "孙皓",
      "步阐",
      "丁固",
      "诸葛靓"
    ],
    "原文": "九月，从西陵督步阐表，徙都武昌，御史大夫丁固、右将军诸葛靓镇建业。",
    "事件翻译": "九月，孙皓听从西陵督步阐的上表，迁都到武昌，命御史大夫丁固、右将军诸葛靓镇守建业。",
    "std_start_year": 265,
    "涉及的集团": [
      "jiang_dong"
    ],
    "所属事件": [],
    "地理信息": [
      "荆州:江夏郡:武昌县"
    ],
    "是否本传": true
  },
  {
    "事件标题": "纪陟弘璆出使魏国",
    "时间": "甘露元年",
    "地点": "洛阳",
    "相关人物": [
      "纪陟",
      "弘璆",
      "晋文帝",
      "魏帝"
    ],
    "原文": "陟、璆至洛，遇晋文帝崩，十一月，乃遣还。",
    "事件翻译": "纪陟、弘璆到达洛阳，正赶上晋文帝去世，十一月，才被遣送回国。",
    "std_start_year": 265,
    "涉及的集团": [
      "jiang_dong"
    ],
    "所属事件": [],
    "地理信息": [
      "司隶:河南尹:洛阳"
    ],
    "是否本传": false
  },
  {
    "事件标题": "孙皓在武昌大赦",
    "时间": "甘露元年",
    "地点": "武昌",
    "相关人物": [
      "孙皓"
    ],
    "原文": "皓至武昌，又大赦。",
    "事件翻译": "孙皓到达武昌，又大赦天下。",
    "std_start_year": 265,
    "涉及的集团": [
      "jiang_dong"
    ],
    "所属事件": [],
    "地理信息": [
      "荆州:江夏郡:武昌县"
    ],
    "是否本传": true
  },
  {
    "事件标题": "孙皓分置始安始兴郡",
    "时间": "甘露元年",
    "地点": "荆州",
    "相关人物": [
      "孙皓"
    ],
    "原文": "以零陵南部为始安郡，桂阳南部为始兴郡。",
    "事件翻译": "将零陵郡南部设置为始安郡，桂阳郡南部设置为始兴郡。",
    "std_start_year": 265,
    "涉及的集团": [
      "jiang_dong"
    ],
    "所属事件": [],
    "地理信息": [
      "荆州:零陵郡",
      "荆州:桂阳郡"
    ],
    "是否本传": true
  },
  {
    "事件标题": "晋受禅",
    "时间": "甘露元年十二月",
    "地点": "洛阳",
    "相关人物": [
      "司马炎",
      "曹奂"
    ],
    "原文": "十二月，晋受禅。",
    "事件翻译": "十二月，晋朝接受禅让。",
    "std_start_year": 265,
    "涉及的集团": [
      "he_nei_sima"
    ],
    "所属事件": [
      "sima_yan_dai_wei"
    ],
    "地理信息": [
      "司隶:河南尹:洛阳"
    ],
    "是否本传": false
  },
  {
    "事件标题": "孙皓派遣张俨、丁忠吊祭晋文帝",
    "时间": "宝鼎元年正月",
    "地点": "洛阳",
    "相关人物": [
      "孙皓",
      "张俨",
      "丁忠",
      "晋文帝"
    ],
    "原文": "宝鼎元年正月，遣大鸿胪张俨、五官中郎将丁忠吊祭晋文帝。及还，俨道病死。[吴录曰：俨字子节，吴人也。弱冠知名，历显位，以博闻多识，拜大鸿胪。使於晋，皓谓俨曰：今南北通好，以君为有出境之才，故相屈行。对曰：皇皇者华，蒙其荣耀，无古人延誉之美，磨厉锋锷，思不辱命。既至，车骑将军贾充、尚书令裴秀、侍中荀勖等欲傲以所不知而不能屈。尚书仆射羊祜、尚书何桢并结缟带之好。]",
    "事件翻译": "宝鼎元年正月，孙皓派遣大鸿胪张俨、五官中郎将丁忠前往洛阳吊祭晋文帝司马昭。等到他们返回时，张俨在途中病逝。",
    "std_start_year": 266,
    "涉及的集团": [
      "jiang_dong"
    ],
    "所属事件": [],
    "地理信息": [
      "司隶:河南尹:洛阳"
    ],
    "是否本传": true
  },
  {
    "事件标题": "丁忠建议孙皓袭击弋阳",
    "时间": "宝鼎元年",
    "地点": "建业",
    "相关人物": [
      "孙皓",
      "丁忠",
      "陆凯",
      "刘纂"
    ],
    "原文": "忠说皓曰：北方守战之具不设，弋阳可袭而取。皓访群臣，镇西大将军陆凯曰：夫兵不得已而用之耳，且三国鼎立已来，更相侵伐，无岁宁居。今强敌新并巴蜀，有兼土之实，而遣使求亲，欲息兵役，不可谓其求援於我。今敌形势方强，而欲徼幸求胜，未见其利也。车骑将军刘纂曰：天生五才，谁能去兵？谲诈相雄，有自来矣。若其有阙，庸可弃乎？宜遣间谍，以观其势。皓阴纳纂言，且以蜀新平，故不行，然遂自绝。",
    "事件翻译": "丁忠劝说孙皓说：北方（晋国）的守战装备不完善，可以袭击并夺取弋阳。孙皓询问群臣意见，镇西大将军陆凯说：战争是不得已才使用的，况且三国鼎立以来，互相侵伐，没有一年安宁。如今强敌刚刚吞并巴蜀，有兼并土地的实力，却派遣使者请求和亲，是想停止战争，不能认为他们是向我们求援。现在敌人形势正强，而想侥幸求胜，看不到好处。车骑将军刘纂说：天生五材，谁能去掉战争？诡诈相争，由来已久。如果敌人有漏洞，怎能放弃？应该派遣间谍，观察他们的形势。孙皓暗中采纳了刘纂的话，并且因为蜀国刚刚平定，所以没有行动，但从此与晋断绝了关系。",
    "std_start_year": 266,
    "涉及的集团": [
      "jiang_dong"
    ],
    "所属事件": [],
    "地理信息": [
      "豫州:汝南郡"
    ],
    "是否本传": true
  },
  {
    "事件标题": "孙皓改元宝鼎并任命陆凯、万彧为丞相",
    "时间": "宝鼎元年八月",
    "地点": "建业",
    "相关人物": [
      "孙皓",
      "陆凯",
      "万彧"
    ],
    "原文": "八月，所在言得大鼎，於是改年，大赦。以陆凯为左丞相，常侍万彧为右丞相。",
    "事件翻译": "八月，各地报告说得到了大鼎，于是改年号（为宝鼎），大赦天下。任命陆凯为左丞相，常侍万彧为右丞相。",
    "std_start_year": 266,
    "涉及的集团": [
      "jiang_dong"
    ],
    "所属事件": [],
    "地理信息": [
      "扬州:丹杨郡:建业县"
    ],
    "是否本传": true
  },
  {
    "事件标题": "永安山贼施但劫持孙谦叛乱",
    "时间": "宝鼎元年冬十月",
    "地点": "永安、乌程、建业",
    "相关人物": [
      "孙皓",
      "施但",
      "孙谦",
      "丁固",
      "诸葛靓"
    ],
    "原文": "冬十月，永安山贼施但等聚众数千人，[吴录曰：永安今武康县也。]劫皓庶弟永安侯谦出乌程，取孙和陵上鼓吹曲盖。比至建业，众万馀人。丁固、诸葛靓逆之於牛屯，大战，但等败走。获谦，谦自杀。[汉晋春秋曰：初望气者云荆州有王气破扬州而建业宫不利，故皓徙武昌，遣使者发民掘荆州界大臣名家冢与山冈连者以厌之。既闻但反，自以为徙土得计也。使数百人鼓噪人建业，杀但妻子，云天子使荆州兵来破扬州贼，以厌前气。]",
    "事件翻译": "冬十月，永安的山贼施但等人聚集了数千人，劫持了孙皓的庶弟永安侯孙谦，从乌程出发，取走了孙和陵墓上的鼓吹曲盖。等到达建业时，部众已有一万多人。丁固、诸葛靓在牛屯迎击，大战，施但等败走。俘获孙谦，孙谦自杀。",
    "std_start_year": 266,
    "涉及的集团": [
      "jiang_dong"
    ],
    "所属事件": [],
    "地理信息": [
      "扬州:吴郡:乌程县",
      "扬州:丹杨郡:建业县"
    ],
    "是否本传": true
  },
  {
    "事件标题": "孙皓分置东阳郡、吴兴郡、邵陵郡",
    "时间": "宝鼎元年",
    "地点": "扬州、荆州",
    "相关人物": [
      "孙皓"
    ],
    "原文": "分会稽为东阳郡，分吴、丹杨为吴兴郡。[皓诏曰：古者分土建国，所以褒赏贤能，广树藩屏。秦毁五等为三十六郡，汉室初兴，闿立乃至百王，因事制宜，盖无常数也。今吴郡阳羡、永安、馀杭、临水及丹杨故鄣、安吉、原乡、於潜诸县，地势水流之便，悉注乌程，既宜立郡以镇山越，且以藩卫明陵，奉承大祭，不亦可乎！其亟分此九县为吴兴郡，治乌程。]以零陵北部为邵陵郡。",
    "事件翻译": "分会稽郡设置东阳郡，分吴郡和丹杨郡设置吴兴郡。又分零陵郡北部设置邵陵郡。",
    "std_start_year": 266,
    "涉及的集团": [
      "jiang_dong"
    ],
    "所属事件": [],
    "地理信息": [
      "扬州:会稽郡",
      "扬州:吴郡",
      "扬州:丹杨郡",
      "荆州:零陵郡"
    ],
    "是否本传": true
  },
  {
    "事件标题": "孙皓还都建业",
    "时间": "宝鼎元年十二月",
    "地点": "武昌、建业",
    "相关人物": [
      "孙皓",
      "滕牧"
    ],
    "原文": "十二月，皓还都建业，卫将军滕牧留镇武昌。",
    "事件翻译": "十二月，孙皓将都城迁回建业，卫将军滕牧留下镇守武昌。",
    "std_start_year": 266,
    "涉及的集团": [
      "jiang_dong"
    ],
    "所属事件": [],
    "地理信息": [
      "扬州:丹杨郡:建业县",
      "荆州:江夏郡:武昌县"
    ],
    "是否本传": true
  },
  {
    "事件标题": "孙皓大赦并命万彧镇守巴丘",
    "时间": "宝鼎二年春",
    "地点": "巴丘",
    "相关人物": [
      "孙皓",
      "万彧"
    ],
    "原文": "二年春，大赦。右丞相万彧上镇巴丘。",
    "事件翻译": "宝鼎二年春天，孙皓大赦天下。右丞相万彧前往巴丘镇守。",
    "std_start_year": 267,
    "涉及的集团": [
      "jiang_dong"
    ],
    "所属事件": [],
    "地理信息": [
      "荆州:长沙郡:巴丘"
    ],
    "是否本传": true
  },
  {
    "事件标题": "孙皓兴建显明宫",
    "时间": "宝鼎二年夏六月",
    "地点": "建业",
    "相关人物": [
      "孙皓",
      "陆凯"
    ],
    "原文": "夏六月，起显明宫，[太康三年地记曰：吴有太初宫，方三百丈，权所起也。昭明宫方五百丈，皓所作也。避晋讳，故曰显明。吴历云：显明在太初之东。江表传曰：皓营新宫，二千石以下皆自入山督摄伐木。又破坏诸营，大开园囿，起土山楼观，穷极伎巧，功役之费以亿万计。陆凯固谏，不从。]冬十二月，皓移居之。",
    "事件翻译": "夏天六月，孙皓开始修建显明宫。[《太康三年地记》说：吴国有太初宫，方圆三百丈，是孙权所建。昭明宫方圆五百丈，是孙皓所建。为避晋朝讳，所以称为显明。《吴历》说：显明宫在太初宫东边。《江表传》说：孙皓营建新宫，二千石以下的官员都要亲自入山监督砍伐木材。又破坏各个军营，大建园林，堆筑土山、楼台观阁，极尽技巧，工程费用数以亿万计。陆凯坚决劝谏，孙皓不听。]冬天十二月，孙皓迁居到显明宫。",
    "std_start_year": 267,
    "涉及的集团": [
      "jiang_dong"
    ],
    "所属事件": [],
    "地理信息": [
      "扬州:丹杨郡:建业县"
    ],
    "是否本传": true
  },
  {
    "事件标题": "孙皓分豫章、庐陵、长沙为安成郡",
    "时间": "宝鼎二年",
    "地点": "豫章、庐陵、长沙",
    "相关人物": [
      "孙皓"
    ],
    "原文": "是岁，分豫章、庐陵、长沙为安成郡。",
    "事件翻译": "这一年，孙皓分豫章、庐陵、长沙三郡的部分地区设置安成郡。",
    "std_start_year": 267,
    "涉及的集团": [
      "jiang_dong"
    ],
    "所属事件": [],
    "地理信息": [
      "扬州:豫章郡",
      "扬州:庐陵郡",
      "荆州:长沙郡"
    ],
    "是否本传": true
  },
  {
    "事件标题": "孙皓任命丁固、孟仁为司徒、司空",
    "时间": "三年春二月",
    "地点": "建业",
    "相关人物": [
      "孙皓",
      "丁固",
      "孟仁"
    ],
    "原文": "三年春二月，以左右御史大夫丁固、孟仁为司徒、司空。[吴书曰：初，固为尚书，梦松树生其腹上，谓人曰：松字十八公也，后十八岁，吾其为公乎！卒如梦焉。]",
    "事件翻译": "三年春二月，孙皓任命左右御史大夫丁固、孟仁为司徒、司空。[吴书记载：当初，丁固任尚书时，梦见松树长在自己肚子上，对人说：松字是十八公，十八年后，我大概会成为三公吧！最终果然如梦境所示。]",
    "std_start_year": 267,
    "涉及的集团": [],
    "所属事件": [],
    "地理信息": [
      "扬州:吴郡:建业县"
    ],
    "是否本传": true
  },
  {
    "事件标题": "孙皓出东关，丁奉至合肥",
    "时间": "秋九月",
    "地点": "东关、合肥",
    "相关人物": [
      "孙皓",
      "丁奉"
    ],
    "原文": "秋九月，皓出东关，丁奉至合肥。",
    "事件翻译": "秋九月，孙皓出兵东关，丁奉到达合肥。",
    "std_start_year": 267,
    "涉及的集团": [],
    "所属事件": [],
    "地理信息": [
      "扬州:九江郡:合肥县",
      "扬州:庐江郡:东关"
    ],
    "是否本传": true
  },
  {
    "事件标题": "孙皓遣刘俊、脩则攻交阯，被晋将毛炅击败",
    "时间": "是岁",
    "地点": "交阯、合浦",
    "相关人物": [
      "孙皓",
      "刘俊",
      "脩则",
      "毛炅"
    ],
    "原文": "是岁，遣交州刺史刘俊、前部督脩则等入击交阯，为晋将毛炅等所破，皆死，兵散还合浦。",
    "事件翻译": "这一年，孙皓派遣交州刺史刘俊、前部督脩则等人进攻交阯，被晋将毛炅等人击败，刘俊、脩则都战死，士兵溃散退回合浦。",
    "std_start_year": 267,
    "涉及的集团": [],
    "所属事件": [],
    "地理信息": [
      "交州",
      "交州:合浦郡"
    ],
    "是否本传": true
  },
  {
    "事件标题": "孙皓立太子及封王",
    "时间": "建衡元年春正月",
    "地点": "建业",
    "相关人物": [
      "孙皓",
      "孙瑾",
      "淮阳王",
      "东平王"
    ],
    "原文": "建衡元年春正月，立子瑾为太子，及淮阳、东平王。",
    "事件翻译": "建衡元年春季正月，孙皓立儿子孙瑾为太子，并封淮阳王和东平王。",
    "std_start_year": 269,
    "涉及的集团": [],
    "所属事件": [],
    "地理信息": [
      "扬州:丹杨郡:建业县"
    ],
    "是否本传": true
  },
  {
    "事件标题": "孙皓改元大赦",
    "时间": "建衡元年冬十月",
    "地点": "建业",
    "相关人物": [
      "孙皓"
    ],
    "原文": "冬十月，改年，大赦。",
    "事件翻译": "冬季十月，孙皓改换年号，大赦天下。",
    "std_start_year": 269,
    "涉及的集团": [],
    "所属事件": [],
    "地理信息": [
      "扬州:丹杨郡:建业县"
    ],
    "是否本传": true
  },
  {
    "事件标题": "左丞相陆凯去世",
    "时间": "建衡元年十一月",
    "地点": "建业",
    "相关人物": [
      "陆凯"
    ],
    "原文": "十一月，左丞相陆凯卒。",
    "事件翻译": "十一月，左丞相陆凯去世。",
    "std_start_year": 269,
    "涉及的集团": [
      "wu_jun_lu"
    ],
    "所属事件": [],
    "地理信息": [
      "扬州:丹杨郡:建业县"
    ],
    "是否本传": false
  },
  {
    "事件标题": "孙皓遣军击交阯",
    "时间": "建衡元年",
    "地点": "合浦",
    "相关人物": [
      "孙皓",
      "虞汜",
      "薛珝",
      "陶璜",
      "李勖",
      "徐存"
    ],
    "原文": "遣监军虞汜、威南将军薛珝、苍梧太守陶璜由荆州，监军李勖、督军徐存从建安海道，皆就合浦击交阯。",
    "事件翻译": "孙皓派遣监军虞汜、威南将军薛珝、苍梧太守陶璜从荆州出发，监军李勖、督军徐存从建安海道出发，都到合浦会合，进攻交阯。",
    "std_start_year": 269,
    "涉及的集团": [],
    "所属事件": [],
    "地理信息": [
      "交州:合浦郡",
      "荆州",
      "扬州:建安郡"
    ],
    "是否本传": true
  },
  {
    "事件标题": "孙皓建衡二年大赦及多事之秋",
    "时间": "建衡二年（公元270年）",
    "地点": "建业、夏口",
    "相关人物": [
      "孙皓",
      "万彧",
      "李勖",
      "冯斐",
      "施绩",
      "何定",
      "徐存",
      "孙秀"
    ],
    "原文": "二年春。万彧还建业。李勖以建安道不通利，杀导将冯斐，引军还。三月，天火烧万馀家，死者七百人。夏四月，左大司马施绩卒。殿中列将何定曰：少府李勖枉杀冯斐，擅彻军退还。勖及徐存家属皆伏诛。秋九月，何定将兵五千人上夏口猎。都督孙秀奔晋。是岁大赦。",
    "事件翻译": "建衡二年春天，万彧回到建业。李勖因为建安海道不通畅，杀死了向导将领冯斐，率领军队返回。三月，天火烧毁了一万多户人家，死了七百人。夏季四月，左大司马施绩去世。殿中列将何定说：少府李勖枉杀冯斐，擅自撤军退回。李勖和徐存的家属都被处死。秋季九月，何定率领五千士兵到夏口打猎。都督孙秀逃奔晋国。这一年实行大赦。",
    "std_start_year": 270,
    "涉及的集团": [],
    "所属事件": [],
    "地理信息": [
      "扬州:丹杨郡:建业县",
      "荆州:江夏郡:夏口"
    ],
    "是否本传": true
  },
  {
    "事件标题": "孙皓大举出行华里",
    "时间": "三年春正月晦",
    "地点": "华里",
    "相关人物": [
      "孙皓",
      "华覈"
    ],
    "原文": "三年春正月晦，皓举大众出华里，皓母及妃妾皆行，东观令华覈等固争，乃还。",
    "事件翻译": "三年春正月最后一天，孙皓率领大队人马从华里出发，他的母亲和妃妾都随行，东观令华覈等人坚决劝阻，于是返回。",
    "std_start_year": 266,
    "涉及的集团": [],
    "所属事件": [],
    "地理信息": [
      "扬州:丹杨郡:华里"
    ],
    "是否本传": true
  },
  {
    "事件标题": "裴松之注引江表传记载孙皓西上洛阳之事",
    "时间": "三年春正月晦",
    "地点": "牛渚",
    "相关人物": [
      "孙皓",
      "刁玄",
      "司马徽",
      "刘廙"
    ],
    "原文": "江表传曰：初丹杨刁玄使蜀，得司马徽与刘廙论运命历数事。玄诈增其文以诳国人曰：黄旗紫盖见於东南，终有天下者，荆、扬之君乎！又得中国降人，言寿春下有童谣曰吴天子当上。皓闻之，喜曰：此天命也。即载其母妻子及后宫数千人，从牛渚陆道西上，云青盖入洛阳，以顺天命。行遇大雪，道涂陷坏，兵士被甲持仗，百人共引一车，寒冻殆死。兵人不堪，皆曰：若遇敌便当倒戈耳。皓闻之，乃还。",
    "事件翻译": "江表传记载：当初丹杨人刁玄出使蜀地，得到了司马徽与刘廙讨论命运历数的事情。刁玄假造并增加内容来欺骗国人说：黄旗紫盖出现在东南，最终拥有天下的，是荆州、扬州的君主吧！又得到中原的降人，说寿春下面有童谣说吴天子应当北上。孙皓听说后，高兴地说：这是天命啊。立即载着他的母亲、妻子、儿子以及后宫数千人，从牛渚陆路西上，声称青盖入洛阳，以顺应天命。路上遇到大雪，道路毁坏，士兵披甲持杖，一百人共同拉一辆车，冻饿几乎死去。士兵不堪忍受，都说：如果遇到敌人就倒戈。孙皓听说后，于是返回。",
    "std_start_year": 266,
    "涉及的集团": [],
    "所属事件": [],
    "地理信息": [
      "扬州:丹杨郡:牛渚"
    ],
    "是否本传": true
  },
  {
    "事件标题": "汜、璜破交阯，擒杀晋将",
    "时间": "三年",
    "地点": "交阯",
    "相关人物": [
      "汜",
      "璜",
      "孙皓"
    ],
    "原文": "是岁，汜、璜破交阯，禽杀晋所置守将，九真、日南皆还属。",
    "事件翻译": "这一年，汜、璜攻破交阯，擒杀晋朝所设置的守将，九真、日南都重新归属吴国。",
    "std_start_year": 266,
    "涉及的集团": [],
    "所属事件": [],
    "地理信息": [
      "交州"
    ],
    "是否本传": false
  },
  {
    "事件标题": "裴松之注引汉晋春秋记载陶璜攻杨稷、毛炅之事",
    "时间": "三年",
    "地点": "交阯",
    "相关人物": [
      "霍弋",
      "杨稷",
      "毛炅",
      "陶璜",
      "孙皓",
      "王约",
      "脩则",
      "脩允",
      "晋武帝"
    ],
    "原文": "汉晋春秋曰：初霍弋遣杨稷、毛炅等戍，与之誓曰：若贼围城，未百日而降者，家属诛；若过百日而城没者，刺史受其罪。稷等日未满而粮尽，乞降於璜。璜不许，而给粮使守。吴人并谏，璜曰：霍弋已死，无能来者，可须其粮尽，然后乃受，使彼来无罪，而我取有义，内训吾民，外怀邻国，不亦可乎！稷、炅粮尽，救不至，乃纳之。华阳国志曰：稷，犍为人。炅，建宁人。稷等城中食尽，死亡者半，将军王约反降，吴人得入城，获稷、炅，皆囚之。孙皓使送稷下都，稷至合浦，欧血死。晋追赠交州刺史。初，毛炅与吴军战，杀前部督脩则。陶璜等以炅壮勇，欲赦之。而则子允固求杀炅，炅亦不为璜等屈，璜等怒，面缚炅诘之，曰：晋贼！炅厉声曰：吴狗，何等为贼？吴人生剖其腹，允割其心肝，骂曰：庸复作贼？炅犹骂不止，曰：尚欲斩汝孙皓，汝父何死狗也！乃斩之。晋武帝闻而哀矜，即诏使炅长子袭爵，馀三子皆关内侯。此与汉晋春秋所说不同。",
    "事件翻译": "汉晋春秋记载：当初霍弋派遣杨稷、毛炅等人戍守，与他们发誓说：如果贼军围城，不到一百天就投降的，家属处死；如果超过一百天而城被攻破的，刺史承担罪责。杨稷等人日期未满而粮食耗尽，向陶璜请求投降。陶璜不答应，反而供给粮食让他们防守。吴人都劝谏，陶璜说：霍弋已死，没有能来救援的，可以等到他们粮食耗尽，然后再接受投降，使他们前来没有罪过，而我们获取有义，对内训导我的民众，对外安抚邻国，不也可以吗！杨稷、毛炅粮食耗尽，救兵不到，于是接纳了他们。华阳国志说：杨稷是犍为人。毛炅是建宁人。杨稷等人城中粮食吃尽，死亡过半，将军王约反叛投降，吴人得以入城，俘获杨稷、毛炅，都囚禁起来。孙皓派人送杨稷到都城，杨稷到达合浦，吐血而死。晋朝追赠他为交州刺史。当初，毛炅与吴军交战，杀死前部督脩则。陶璜等人因为毛炅壮勇，想赦免他。但脩则的儿子脩允坚持要求杀死毛炅，毛炅也不向陶璜等人屈服，陶璜等人发怒，当面捆绑毛炅责问他说：晋贼！毛炅厉声说：吴狗，什么是贼？吴人活活剖开他的肚子，脩允割下他的心肝，骂道：还能再做贼吗？毛炅仍然骂个不停，说：还要杀你孙皓，你父亲是什么死狗！于是杀了他。晋武帝听说后哀怜他，立即下诏让毛炅的长子继承爵位，其余三个儿子都封为关内侯。这与汉晋春秋所说不同。",
    "std_start_year": 266,
    "涉及的集团": [],
    "所属事件": [],
    "地理信息": [
      "交州"
    ],
    "是否本传": false
  },
  {
    "事件标题": "孙皓大赦并分交阯为新昌郡",
    "时间": "三年",
    "地点": "交阯",
    "相关人物": [
      "孙皓"
    ],
    "原文": "大赦，分交阯为新昌郡。",
    "事件翻译": "大赦天下，分交阯设置新昌郡。",
    "std_start_year": 266,
    "涉及的集团": [],
    "所属事件": [],
    "地理信息": [
      "交州"
    ],
    "是否本传": true
  },
  {
    "事件标题": "诸将破扶严，置武平郡",
    "时间": "三年",
    "地点": "扶严",
    "相关人物": [
      "孙皓"
    ],
    "原文": "诸将破扶严，置武平郡。",
    "事件翻译": "诸将攻破扶严，设置武平郡。",
    "std_start_year": 266,
    "涉及的集团": [],
    "所属事件": [],
    "地理信息": [
      "交州"
    ],
    "是否本传": false
  },
  {
    "事件标题": "孙皓任命范慎为太尉",
    "时间": "三年",
    "地点": "建业",
    "相关人物": [
      "孙皓",
      "范慎"
    ],
    "原文": "以武昌督范慎为太尉。",
    "事件翻译": "任命武昌督范慎为太尉。",
    "std_start_year": 266,
    "涉及的集团": [],
    "所属事件": [],
    "地理信息": [
      "扬州:丹杨郡:建业县"
    ],
    "是否本传": true
  },
  {
    "事件标题": "丁奉、孟仁去世",
    "时间": "三年",
    "地点": "建业",
    "相关人物": [
      "孙皓",
      "丁奉",
      "孟仁"
    ],
    "原文": "右大司马丁奉、司空孟仁卒。",
    "事件翻译": "右大司马丁奉、司空孟仁去世。",
    "std_start_year": 266,
    "涉及的集团": [],
    "所属事件": [],
    "地理信息": [
      "扬州:丹杨郡:建业县"
    ],
    "是否本传": false
  },
  {
    "事件标题": "裴松之注引吴录记载孟仁生平",
    "时间": "三年",
    "地点": "江夏",
    "相关人物": [
      "孟仁",
      "李肃",
      "朱据",
      "孙权"
    ],
    "原文": "吴录曰：仁字恭武，江夏人也，本名宗，避皓字，易焉。少从南阳李肃学。其母为作厚褥大被，或问其故，母曰：小儿无德致客，学者多贫，故为广被，庶可得与气类接也。其读书夙夜不懈，肃奇之，曰：卿宰相器也。初为骠骑将军朱据军吏，将母在营。既不得志，又夜雨屋漏，因起涕泣，以谢其母，母曰：但当勉之，何足泣也？据亦稍知之，除为监池司马。自能结网，手以捕鱼，作鲊寄母，母因以还之，曰：汝为鱼官，而鲊寄我，非避嫌也。迁吴令。时皆不得将家之官，每得时物，来以寄母，常不先食。及闻母亡，犯禁委官，语在权传。特为减死一等，复使为官，盖优之也。楚国先贤传曰：宗母嗜笋，冬节将至。时笋尚未生，宗入竹林哀叹，而笋为之出，得以供母，皆以为至孝之所致感。累迁光禄勋，遂至公矣。",
    "事件翻译": "吴录记载：孟仁字恭武，江夏人，本名宗，避孙皓的字，改为仁。年少时跟随南阳李肃学习。他的母亲为他做厚褥大被，有人问原因，母亲说：小儿无德招客，学者多贫，所以做宽大的被子，或许可以结交同类。他读书日夜不懈，李肃认为奇异，说：你是宰相之器。起初任骠骑将军朱据的军吏，带母亲在军营。不得志，又夜雨屋漏，于是哭泣向母亲道歉，母亲说：只管努力，何足哭泣？朱据也逐渐了解他，任命为监池司马。自己能结网，亲手捕鱼，做腌鱼寄给母亲，母亲却还给他，说：你为鱼官，却寄腌鱼给我，不是避嫌。升任吴令。当时都不准带家眷上任，每次得到时鲜，就寄给母亲，常常不先吃。等到听说母亲去世，违禁弃官，记载在孙权传。特为减死一等，再让他做官，大概是优待他。楚国先贤传记载：孟宗的母亲喜欢吃笋，冬至将至。当时笋尚未生，孟宗进入竹林哀叹，笋于是长出，得以供奉母亲，都认为是至孝感动所致。累迁光禄勋，于是做到三公。",
    "std_start_year": 266,
    "涉及的集团": [],
    "所属事件": [],
    "地理信息": [
      "荆州:江夏郡"
    ],
    "是否本传": false
  },
  {
    "事件标题": "西苑言凤凰集，改明年元",
    "时间": "三年",
    "地点": "西苑",
    "相关人物": [
      "孙皓"
    ],
    "原文": "西苑言凤凰集，改明年元。",
    "事件翻译": "西苑报告有凤凰聚集，于是改明年年号。",
    "std_start_year": 266,
    "涉及的集团": [],
    "所属事件": [],
    "地理信息": [
      "扬州:丹杨郡:建业县"
    ],
    "是否本传": true
  },
  {
    "事件标题": "孙皓征西陵督步阐，步阐据城降晋",
    "时间": "凤皇元年秋八月",
    "地点": "西陵",
    "相关人物": [
      "孙皓",
      "步阐",
      "陆抗"
    ],
    "原文": "凤皇元年秋八月，徵西陵督步阐。阐不应，据城降晋。遣乐乡都督陆抗围取阐，阐众悉降。阐及同计数十人皆夷三族。大赦。",
    "事件翻译": "凤凰元年（272年）秋季八月，孙皓征召西陵督步阐。步阐不服从命令，占据西陵城投降了晋朝。孙皓派遣乐乡都督陆抗包围并攻取西陵，步阐的部众全部投降。步阐及其同谋的数十人都被诛灭三族。孙皓随后大赦天下。",
    "std_start_year": 272,
    "涉及的集团": [
      "jiang_dong"
    ],
    "所属事件": [
      "xiangling_zhi_zhan"
    ],
    "地理信息": [
      "荆州:南郡:西陵县"
    ],
    "是否本传": true
  },
  {
    "事件标题": "右丞相万彧被谴忧死",
    "时间": "凤皇元年",
    "地点": "建业",
    "相关人物": [
      "孙皓",
      "万彧",
      "丁奉",
      "留平"
    ],
    "原文": "是岁右丞相万彧被谴忧死，徙其子弟於庐陵。[江表传曰：初皓游华里，彧与丁奉、留平密谋曰：此行不急，若至华里不归，社稷事重，不得不自还。此语颇泄。皓闻知，以彧等旧臣，且以计忍而阴衔之。后因会，以毒酒饮彧，传酒人私减之。又饮留平，平觉之，服他药以解，得不死。彧自杀。平忧懑，月馀亦死。]",
    "事件翻译": "这一年，右丞相万彧被孙皓谴责，忧愤而死，他的子弟被流放到庐陵。[《江表传》记载：当初孙皓出游华里，万彧与丁奉、留平密谋说：“这次出行不紧急，如果到了华里不回来，国家大事重要，我们不得不自己返回。”这些话泄露了。孙皓听说后，因为万彧等人是旧臣，暂且忍耐，但内心怀恨。后来在一次宴会上，孙皓用毒酒给万彧喝，传酒的人私下减少了毒药。又给留平喝，留平察觉了，服用其他药物解毒，得以不死。万彧自杀。留平忧愤，一个多月后也死了。]",
    "std_start_year": 272,
    "涉及的集团": [
      "jiang_dong"
    ],
    "所属事件": [],
    "地理信息": [
      "扬州:丹杨郡:建业县"
    ],
    "是否本传": true
  },
  {
    "事件标题": "何定奸秽事发被诛",
    "时间": "凤皇元年",
    "地点": "建业",
    "相关人物": [
      "孙皓",
      "何定",
      "张布",
      "李勖",
      "奚熙",
      "贺惠",
      "徐粲"
    ],
    "原文": "何定奸秽发闻，伏诛。皓以其恶似张布，追改定名为布。[江表传曰：定，汝南人，本孙权给使也，后出补吏。定佞邪僣媚，自表先帝旧人，求还内侍，皓以为楼下都尉，典知酤籴事，专为威福。而皓信任，委以众事。定为子求少府李勖女，不许。定挟忿谮勖於皓，皓尺口诛之，焚其尸。定又使诸将各上好犬，皆千里远求，一犬至直数千匹。御犬率具缨，直钱一万。一犬一兵，养以捕兔供厨。所获无几。吴人皆归罪於定，而皓以为忠勤，赐爵列侯。吴历曰：中书郎奚熙谮宛陵令贺惠。惠，劭弟也。遣使者徐粲讯治，熙又谮粲顾护不即决断。皓遣使就宛陵斩粲，收惠付狱。会赦得免。]",
    "事件翻译": "何定奸邪污秽的行为被揭露，被处死。孙皓因为他的罪恶与张布相似，追改何定的名字为布。[《江表传》记载：何定是汝南人，本来是孙权的给使，后来出朝补任官吏。何定奸佞谄媚，自称是先帝的旧人，请求回宫担任内侍，孙皓任命他为楼下都尉，掌管酿酒和买粮的事务，专横跋扈，作威作福。孙皓信任他，把许多事情交给他。何定为儿子向少府李勖的女儿求婚，李勖不同意。何定怀恨在心，在孙皓面前诬陷李勖，孙皓将李勖全家诛杀，并焚烧了他的尸体。何定又让各位将领各自进献好狗，都从千里之外寻求，一只狗价值数千匹绢。御犬都配有缨络，价值一万钱。一只狗配备一名士兵，养着用来捕兔供厨房。所获不多。吴国人都归罪于何定，但孙皓认为他忠诚勤勉，赐爵列侯。《吴历》记载：中书郎奚熙诬陷宛陵令贺惠。贺惠是贺劭的弟弟。孙皓派使者徐粲审讯处理，奚熙又诬陷徐粲袒护贺惠而不立即判决。孙皓派使者到宛陵斩杀了徐粲，逮捕贺惠入狱。恰逢大赦得以免罪。]",
    "std_start_year": 272,
    "涉及的集团": [
      "jiang_dong"
    ],
    "所属事件": [],
    "地理信息": [
      "扬州:丹杨郡:建业县"
    ],
    "是否本传": true
  },
  {
    "事件标题": "孙皓改封诸王并大赦",
    "时间": "凤皇二年",
    "地点": "建业",
    "相关人物": [
      "孙皓",
      "陆抗",
      "丁固"
    ],
    "原文": "二年春三月，以陆抗为大司马。司徒丁固卒。秋九月，改封淮阳为鲁，东平为齐，又封陈留、章陵等九王，凡十一王，王给三千兵。大赦。",
    "事件翻译": "凤皇二年春季三月，孙皓任命陆抗为大司马。司徒丁固去世。秋季九月，改封淮阳王为鲁王，东平王为齐王，又封陈留、章陵等九位王，总共十一位王，每位王配给三千士兵。大赦天下。",
    "std_start_year": 273,
    "涉及的集团": [
      "jiang_dong"
    ],
    "所属事件": [],
    "地理信息": [
      "扬州:丹杨郡:建业县"
    ],
    "是否本传": true
  },
  {
    "事件标题": "孙皓宠妾劫掠百姓，陈声被处死",
    "时间": "凤皇二年",
    "地点": "建业",
    "相关人物": [
      "孙皓",
      "陈声",
      "孙皓爱妾"
    ],
    "原文": "皓爱妾或使人至市劫夺百姓财物，司市中郎将陈声，素皓幸臣也，恃皓宠遇，绳之以法。妾以愬皓，皓大怒，假他事烧锯断声头，投其身於四望之下。",
    "事件翻译": "孙皓的宠妾派人到市场上抢夺百姓财物，司市中郎将陈声，一向是孙皓的宠臣，依仗孙皓的宠遇，依法处置了这件事。宠妾向孙皓告状，孙皓大怒，假借其他罪名用烧红的锯子锯断陈声的头，将他的尸体扔到四望台下。",
    "std_start_year": 273,
    "涉及的集团": [
      "jiang_dong"
    ],
    "所属事件": [],
    "地理信息": [
      "扬州:丹杨郡:建业县"
    ],
    "是否本传": true
  },
  {
    "事件标题": "太尉范慎去世",
    "时间": "凤皇二年",
    "地点": "建业",
    "相关人物": [
      "孙皓",
      "范慎"
    ],
    "原文": "是岁，太尉范慎卒。",
    "事件翻译": "这一年，太尉范慎去世。",
    "std_start_year": 273,
    "涉及的集团": [
      "jiang_dong"
    ],
    "所属事件": [],
    "地理信息": [
      "扬州:丹杨郡:建业县"
    ],
    "是否本传": true
  },
  {
    "事件标题": "孙皓处理会稽妖言事件",
    "时间": "三年",
    "地点": "建安",
    "相关人物": [
      "孙皓",
      "章安侯奋",
      "奚熙",
      "郭诞",
      "邵畴"
    ],
    "原文": "三年，会稽妖言章安侯奋当为天子。临海太守奚熙与会稽太守郭诞书，非论国政。诞但白熙书，不白妖言，送付建安作船。[会稽邵氏家传曰：邵畴字温伯，时为诞功曹。诞被收，惶遽无以自明。畴进曰：畴今自在，畴之事，明府何忧？遂诣吏自列，云不白妖言，事由于己，非府君罪。吏上畴辞，皓怒犹盛。畴虑诞卒不免，遂自杀以证之。临亡，置辞曰：畴生长边陲，不闲教道，得以门资，厕身本郡，逾越侪类，位极朝右，不能赞扬盛化，养之以福。今妖讹横兴，干国乱纪，畴以噂之语，本非事实，虽家诵人咏，不足有虑。天下重器，而匹夫横议，疾其丑声，不忍闻见，欲含垢藏疾，不彰之翰笔，镇躁归静，使之自息。愚心勤勤，每执斯旨，故诞屈其所是，默以见从。此之为愆，实由於畴。谨不敢逃死，归罪有司，唯乞天鉴，特垂清察。吏收畴丧，得辞以闻，皓乃免诞大刑，送付建安作船。畴亡时，年四十。皓嘉畴节义，诏郡县图形庙堂。]遣三郡督何植收熙，熙发兵自卫，断绝海道。熙部曲杀熙，送首建业，夷三族。秋七月，遣使者二十五人分至州郡，科出亡叛。大司马陆抗卒。自改年及是岁，连大疫。分郁林为桂林郡。",
    "事件翻译": "三年，会稽有谣言说章安侯孙奋应当做天子。临海太守奚熙写信给会稽太守郭诞，非议国政。郭诞只报告了奚熙的信，没有报告谣言，被押送到建安去造船。邵畴是郭诞的功曹，他主动承担责任，自杀以证明郭诞无罪。孙皓表彰了邵畴的节义，下令郡县在庙堂中绘制他的画像。孙皓派三郡督何植逮捕奚熙，奚熙发兵自卫，断绝海道，但被部下杀死，首级送到建业，并被夷灭三族。秋七月，孙皓派二十五名使者分赴各州郡，清查逃亡叛变的人。大司马陆抗去世。从改年号到这一年，连续发生大瘟疫。分郁林郡设立桂林郡。",
    "std_start_year": 276,
    "涉及的集团": [
      "jiang_dong"
    ],
    "所属事件": [],
    "地理信息": [
      "扬州:会稽郡",
      "扬州:建安郡",
      "扬州:吴郡:建业",
      "交州:郁林郡"
    ],
    "是否本传": true
  },
  {
    "事件标题": "吴郡发现刻字银器，孙皓大赦改元天册",
    "时间": "天册元年",
    "地点": "吴郡",
    "相关人物": [
      "孙皓"
    ],
    "原文": "天册元年，吴郡言掘地得银，长一尺，广三分，刻上有年月字，於是大赦，改年。",
    "事件翻译": "天册元年，吴郡报告说从地下挖出一块银，长一尺，宽三分，上面刻有年月字样，于是孙皓大赦天下，改年号为天册。",
    "std_start_year": 275,
    "涉及的集团": [],
    "所属事件": [],
    "地理信息": [
      "扬州:吴郡"
    ],
    "是否本传": true
  },
  {
    "事件标题": "孙皓因临平湖开通及得石函改元大赦",
    "时间": "天玺元年",
    "地点": "吴郡临平湖",
    "相关人物": [
      "孙皓"
    ],
    "原文": "天玺元年，吴郡言临平湖自汉末草秽壅塞，今更开通。长老相传，此湖塞，天下乱，此湖开，天下平。又於湖边得石函，中有小石，青白色，长四寸，广二寸馀，刻上作皇帝字，於是改年，大赦。",
    "事件翻译": "天玺元年，吴郡报告说临平湖从汉末以来被杂草污物堵塞，如今重新开通。老人们相传，这个湖堵塞，天下就大乱；这个湖开通，天下就太平。又在湖边得到一个石匣，里面有一块小石头，青白色，长四寸，宽二寸多，上面刻有皇帝字样，于是改年号，大赦天下。",
    "std_start_year": 276,
    "涉及的集团": [],
    "所属事件": [],
    "地理信息": [
      "扬州:吴郡"
    ],
    "是否本传": true
  },
  {
    "事件标题": "孙皓斩杀会稽太守车浚和湘东太守张咏",
    "时间": "天玺元年",
    "地点": "会稽郡、湘东郡",
    "相关人物": [
      "孙皓",
      "车浚",
      "张咏"
    ],
    "原文": "会稽太守车浚、湘东太守张咏不出算缗，就在所斩之，徇首诸郡。",
    "事件翻译": "会稽太守车浚、湘东太守张咏不缴纳算缗钱，孙皓就在当地将他们斩杀，并将首级在各郡示众。",
    "std_start_year": 276,
    "涉及的集团": [],
    "所属事件": [],
    "地理信息": [
      "扬州:会稽郡",
      "荆州:长沙郡"
    ],
    "是否本传": true
  },
  {
    "事件标题": "裴松之注引江表传记载车浚被斩及熊睦被杀",
    "时间": "天玺元年",
    "地点": "不详",
    "相关人物": [
      "孙皓",
      "车浚",
      "熊睦"
    ],
    "原文": "[江表传曰：浚在公清忠，值郡荒旱，民无资粮，表求振贷。皓谓浚欲树私恩，遣人枭首。又尚书熊睦见皓酷虐，微有所谏，皓使人以刀环撞杀之，身无完肌。]",
    "事件翻译": "江表传说：车浚为官清廉忠诚，正值郡中荒旱，百姓没有粮食，他上表请求赈贷。孙皓认为车浚想树立私恩，派人将他斩首示众。又尚书熊睦看到孙皓残酷暴虐，稍微有所劝谏，孙皓就让人用刀环撞杀他，身上没有完整的肌肤。",
    "std_start_year": 276,
    "涉及的集团": [],
    "所属事件": [],
    "地理信息": [],
    "是否本传": false
  },
  {
    "事件标题": "孙楷投降晋朝",
    "时间": "天玺元年秋八月",
    "地点": "不详",
    "相关人物": [
      "孙皓",
      "孙楷"
    ],
    "原文": "秋八月，京下督孙楷降晋。",
    "事件翻译": "秋季八月，京下督孙楷投降晋朝。",
    "std_start_year": 276,
    "涉及的集团": [],
    "所属事件": [],
    "地理信息": [],
    "是否本传": true
  },
  {
    "事件标题": "历阳山出现石文祥瑞",
    "时间": "天玺元年",
    "地点": "鄱阳郡历阳县",
    "相关人物": [
      "孙皓"
    ],
    "原文": "鄱阳言历阳山石文理成字，凡二十，云楚九州渚，吴九州都，扬州士，作天子，四世治，太平始。",
    "事件翻译": "鄱阳报告说历阳山上的石头纹理形成文字，共二十个字，说：楚九州渚，吴九州都，扬州士，作天子，四世治，太平始。",
    "std_start_year": 276,
    "涉及的集团": [],
    "所属事件": [],
    "地理信息": [
      "扬州:鄱阳郡"
    ],
    "是否本传": true
  },
  {
    "事件标题": "裴松之注引江表传记载石印祥瑞及孙皓反应",
    "时间": "天玺元年",
    "地点": "历阳县",
    "相关人物": [
      "孙皓",
      "历阳长",
      "巫祝"
    ],
    "原文": "[江表传曰：历阳县有石山临水，高百丈，其三十丈所，有七穿骈罗，穿中色黄赤，不与本体相似，俗相传谓之石印。又云，石印封发，天下当太平。下有祠屋，巫祝言石印神有三郎。时历阳长表上言石印发，皓遣使以太牢祭历山。巫言，石印三郎说天下方太平。使者作高梯，上看印文，诈以朱书石作二十字，还以启皓。皓大喜曰：吴当为九州作都、渚乎！从大皇帝逮孤四世矣，太平之主，非孤复谁？重遣使，以印绶拜三郎为王，又刻石立铭，褒赞灵德，以答休祥。]",
    "事件翻译": "江表传说：历阳县有座石山临水，高一百丈，在三十丈高处，有七个孔洞并列，孔中颜色黄赤，与本体不同，民间相传称为石印。又说，石印开启，天下应当太平。山下有祠屋，巫祝说石印神有三个郎君。当时历阳县长上表说石印开启，孙皓派使者用太牢祭祀历山。巫祝说，石印三郎说天下正太平。使者制作高梯，上去看印文，用朱砂在石上伪造了二十个字，回来禀告孙皓。孙皓大喜说：吴国应当为九州作都、渚吗！从大皇帝到我共四代了，太平之主，不是我又是谁？再次派遣使者，用印绶拜三郎为王，又刻石立铭，褒赞神灵的德行，以回报祥瑞。",
    "std_start_year": 276,
    "涉及的集团": [],
    "所属事件": [],
    "地理信息": [
      "扬州:九江郡:历阳县"
    ],
    "是否本传": false
  },
  {
    "事件标题": "孙皓因阳羡山石室祥瑞封禅国山并改元",
    "时间": "天玺元年",
    "地点": "吴兴阳羡县",
    "相关人物": [
      "孙皓",
      "董朝",
      "周处"
    ],
    "原文": "又吴兴阳羡山有空石，长十馀丈，名曰石室，在所表为大瑞。乃遣兼司徒董朝、兼太常周处至阳羡县，封襌国山。改明年元，大赦，以协石文。",
    "事件翻译": "又吴兴阳羡山有一块空心石头，长十多丈，名叫石室，当地官员上表称是大祥瑞。于是派遣兼司徒董朝、兼太常周处到阳羡县，在国山举行封禅典礼。改明年年号，大赦天下，以与石文相应。",
    "std_start_year": 276,
    "涉及的集团": [],
    "所属事件": [],
    "地理信息": [
      "扬州:吴郡:阳羡县"
    ],
    "是否本传": true
  },
  {
    "事件标题": "孙慎出江夏、汝南烧略居民",
    "时间": "天纪元年夏",
    "地点": "江夏、汝南",
    "相关人物": [
      "孙皓",
      "孙慎"
    ],
    "原文": "天纪元年夏，夏口督孙慎出江夏、汝南，烧略居民。",
    "事件翻译": "天纪元年夏天，夏口督孙慎出兵江夏、汝南，焚烧掠夺当地居民。",
    "std_start_year": 277,
    "涉及的集团": [
      "jiang_dong"
    ],
    "所属事件": [],
    "地理信息": [
      "荆州:江夏郡",
      "豫州:汝南郡"
    ],
    "是否本传": true
  },
  {
    "事件标题": "张俶因奸情被诛",
    "时间": "天纪元年",
    "地点": "建业",
    "相关人物": [
      "孙皓",
      "张俶"
    ],
    "原文": "初，驺子张俶多所谮白，累迁为司直中郎将，封侯，甚见宠爱，是岁奸情发闻，伏诛。[江表传曰：俶父，会稽山阴县卒也，知俶不良，上表云：若用俶为司直，有罪乞不从坐。皓许之。俶表立弹曲二十人，专纠司不法，於是爱恶相攻，互相谤告。弹曲承言，收系囹圄，听讼失理，狱以贿成。人民穷困，无所措手足。俶奢淫无厌，取小妻三十馀人，擅杀无辜，众奸并发，父子俱见车裂。]",
    "事件翻译": "起初，驺子张俶多次进谗言，逐渐升迁为司直中郎将，封侯，很受宠爱，这一年他的奸情败露，被处死。[江表传记载：张俶的父亲是会稽山阴县的士卒，知道张俶品行不良，上表说：如果任用张俶为司直，有罪请求不要连坐。孙皓同意了。张俶上表设立弹曲二十人，专门纠察不法行为，于是爱恶相攻，互相诽谤告发。弹曲根据告发，逮捕入狱，审理案件失去公正，狱讼靠贿赂决定。人民穷困，手足无措。张俶奢侈淫乱无度，娶小妻三十多人，擅自杀害无辜，各种奸恶并发，父子都被车裂。]",
    "std_start_year": 277,
    "涉及的集团": [
      "jiang_dong"
    ],
    "所属事件": [],
    "地理信息": [
      "扬州:会稽郡:山阴县"
    ],
    "是否本传": true
  },
  {
    "事件标题": "孙皓立十一王并大赦",
    "时间": "天纪二年秋七月",
    "地点": "建业",
    "相关人物": [
      "孙皓"
    ],
    "原文": "二年秋七月，立成纪、宣威等十一王，王给三千兵，大赦。",
    "事件翻译": "天纪二年秋季七月，孙皓册立成纪王、宣威王等十一位王，每位王配给三千士兵，并实行大赦。",
    "std_start_year": 278,
    "涉及的集团": [],
    "所属事件": [],
    "地理信息": [
      "扬州:丹杨郡:建业县"
    ],
    "是否本传": true
  },
  {
    "事件标题": "郭马在广州反叛",
    "时间": "天纪三年夏",
    "地点": "广州",
    "相关人物": [
      "孙皓",
      "郭马",
      "脩允",
      "何典",
      "王族",
      "吴述",
      "殷兴",
      "虞授"
    ],
    "原文": "三年夏，郭马反。马本合浦太守脩允部曲督。允转桂林太守，疾病，住广州，先遣马将五百兵至郡安抚诸夷。允死，兵当分给，马等累世旧军，不乐离别。皓时又科实广州户口，马与部曲将何典、王族、吴述、殷兴等因此恐动兵民，合聚人众，攻杀广州督虞授。马自号都督交、广二州诸军事、安南将军，兴广州刺史，述南海太守。典攻苍梧，族攻始兴。",
    "事件翻译": "天纪三年夏天，郭马反叛。郭马原本是合浦太守脩允的部曲督。脩允调任桂林太守，因病停留在广州，先派郭马率领五百士兵到桂林郡安抚各夷族。脩允死后，这些士兵应当被分散调拨，但郭马等人是累世旧军，不愿分离。孙皓当时又核查广州户口，郭马与部曲将何典、王族、吴述、殷兴等人因此煽动士兵和百姓，聚集人马，攻杀广州督虞授。郭马自称都督交、广二州诸军事、安南将军，任命吴述为广州刺史，殷兴为南海太守。何典攻打苍梧，王族攻打始兴。",
    "std_start_year": 279,
    "涉及的集团": [],
    "所属事件": [],
    "地理信息": [
      "交州:合浦郡",
      "交州:苍梧郡",
      "荆州:始兴郡"
    ],
    "是否本传": true
  },
  {
    "事件标题": "孙皓因谶言迁徙公孙姓者",
    "时间": "天纪三年夏",
    "地点": "广州",
    "相关人物": [
      "孙皓",
      "郭马"
    ],
    "原文": "[汉晋春秋曰：先是，吴有说谶者曰：吴之败，兵起南裔，亡吴者公孙也。皓闻之，文武职位至于卒伍有姓公孙者，皆徙於广州，不令停江边。及闻马反，大惧曰：此天亡也。]",
    "事件翻译": "《汉晋春秋》记载：在此之前，吴国有解说谶语的人说：吴国的败亡，军队起于南方边陲，灭亡吴国的人是公孙氏。孙皓听说后，将文武职位乃至士卒中姓公孙的人，全部迁徙到广州，不让他们停留在长江边。等到听说郭马反叛，非常恐惧地说：这是天要亡我啊。",
    "std_start_year": 279,
    "涉及的集团": [],
    "所属事件": [],
    "地理信息": [
      "交州:广州"
    ],
    "是否本传": true
  },
  {
    "事件标题": "孙皓任命张悌、何植、滕循等官职并讨伐郭马",
    "时间": "天纪三年八月",
    "地点": "建业",
    "相关人物": [
      "孙皓",
      "张悌",
      "何植",
      "滕循",
      "陶濬",
      "陶璜",
      "王族",
      "刘略",
      "徐旗"
    ],
    "原文": "八月，以军师张悌为丞相，牛渚都督何植为司徒。执金吾滕循为司空，未拜，转镇南将军，假节领广州牧，率万人从东道讨马，与族遇于始兴，未得前。马杀南海太守刘略，逐广州刺史徐旗。皓又遣徐陵督陶濬将七千人从西道，命交州牧陶璜部伍所领及合浦、郁林诸郡兵，当与东西军共击马。",
    "事件翻译": "八月，孙皓任命军师张悌为丞相，牛渚都督何植为司徒。执金吾滕循为司空，滕循尚未正式受拜，又转任镇南将军，假节兼任广州牧，率领一万人从东道讨伐郭马，与王族在始兴相遇，未能前进。郭马杀死南海太守刘略，驱逐广州刺史徐旗。孙皓又派遣徐陵督陶濬率领七千人从西道进军，命令交州牧陶璜部署所部及合浦、郁林等郡的军队，应当与东西两路军队共同攻击郭马。",
    "std_start_year": 279,
    "涉及的集团": [],
    "所属事件": [],
    "地理信息": [
      "交州:南海郡",
      "交州:合浦郡",
      "交州:郁林郡",
      "荆州:始兴郡"
    ],
    "是否本传": true
  },
  {
    "事件标题": "孙皓以祥瑞任命黄耇、吴平为郎",
    "时间": "天纪三年",
    "地点": "建业",
    "相关人物": [
      "孙皓",
      "黄耇",
      "吴平"
    ],
    "原文": "有鬼目菜生工人黄耇家，依缘枣树，长丈馀，茎广四寸，厚三分。又有买菜生工人吴平家，高四尺，厚三分，如枇杷形，上广尺八寸，下茎广五寸，两边生叶绿色。东观案图，名鬼目作芝草，买菜作平虑草，遂以耇为侍芝郎，平为平虑郎，皆银印青绶。",
    "事件翻译": "有鬼目菜生长在工匠黄耇家中，攀附在枣树上，长一丈多，茎宽四寸，厚三分。又有买菜生长在工匠吴平家中，高四尺，厚三分，形状像枇杷，上部宽一尺八寸，下部茎宽五寸，两边长有绿色叶子。东观查阅图籍，将鬼目菜命名为芝草，将买菜命名为平虑草，于是任命黄耇为侍芝郎，吴平为平虑郎，都授予银印青绶。",
    "std_start_year": 279,
    "涉及的集团": [],
    "所属事件": [],
    "地理信息": [
      "扬州:丹杨郡:建业县"
    ],
    "是否本传": true
  },
  {
    "事件标题": "晋军多路伐吴",
    "时间": "咸宁五年冬",
    "地点": "涂中、牛渚、武昌、夏口、江陵、长江",
    "相关人物": [
      "司马伷",
      "王浑",
      "周浚",
      "王戎",
      "胡奋",
      "杜预",
      "王濬",
      "唐彬",
      "贾充",
      "陶濬"
    ],
    "原文": "冬，晋命镇东大将军司马伷向涂中，安东将军王浑、扬州刺史周浚向牛渚，建威将军王戎向武昌，平南将军胡奋向夏口，镇南将军杜预向江陵，龙骧将军王濬、广武将军唐彬浮江东下，太尉贾充为大都督，量宜处要，尽军势之中。陶濬至武昌，闻北军大出，停驻不前。",
    "事件翻译": "冬天，晋朝命令镇东大将军司马伷进军涂中，安东将军王浑、扬州刺史周浚进军牛渚，建威将军王戎进军武昌，平南将军胡奋进军夏口，镇南将军杜预进军江陵，龙骧将军王濬、广武将军唐彬沿长江顺流东下，太尉贾充担任大都督，根据情况部署要害，充分发挥军队的威力。陶濬到达武昌，听说晋朝大军出动，便停驻不前。",
    "std_start_year": 279,
    "涉及的集团": [
      "he_nei_sima",
      "qiao_jun_cao_xiahou"
    ],
    "所属事件": [
      "jin_mie_wu"
    ],
    "地理信息": [
      "扬州:丹杨郡:涂中",
      "扬州:丹杨郡:牛渚",
      "荆州:江夏郡:武昌",
      "荆州:江夏郡:夏口",
      "荆州:南郡:江陵"
    ],
    "是否本传": true
  },
  {
    "事件标题": "孙皓暴政导致上下离心",
    "时间": "264-280年",
    "地点": "建业",
    "相关人物": [
      "孙皓",
      "岑昬",
      "庾峻",
      "李仁"
    ],
    "原文": "初，皓每宴会群臣，无不咸令沈醉。置黄门郎十人，特不与酒，侍立终日，为司过之吏。宴罢之后，各奏其阙失，迕视之咎，谬言之愆，罔有不举。大者即加威刑，小者辄以为罪。后宫数千，而采择无已。又激水入宫，宫人有不合意者，辄杀流之。或剥人之面，或凿人之眼。岑昬险谀贵幸，致位九列，好兴功役，众所患苦。是以上下离心，莫为皓尽力，盖积恶已极，不复堪命故也。[吴平后，晋侍中庾峻等问皓侍中李仁曰：闻吴主披人面，刖人足，有诸乎？仁曰：以告者过也。君子恶居下流，天下之恶皆归焉。盖此事也，若信有之，亦不足怪。昔唐、虞五刑，三代七辟，肉刑之制，未为酷虐。皓为一国之主，秉杀生之柄，罪人陷法，加之以惩，何足多罪！夫受尧诛者不能无怨，受桀赏者不能无慕，此人情也。又问曰：云归命侯乃恶人横睛逆视，皆凿其眼，有诸乎？仁曰：亦无此事，传之者谬耳。曲礼曰视天子由袷以下，视诸侯由颐以下，视大夫由衡，视士则平面，得游目五步之内；视上於衡则傲，下於带则忧，旁则邪。以礼视瞻，高下不可不慎，况人君乎哉？视人君相迕，是乃礼所谓傲慢；傲慢则无礼，无礼则不臣，不臣则犯罪，犯罪则陷不测矣。正使有之，将有何失？凡仁所答，峻等皆善之，文多不悉载。]",
    "事件翻译": "当初，孙皓每次宴会群臣，无不强迫大家喝醉。他设置十名黄门郎，特意不给他们酒喝，让他们整天侍立，作为纠察过失的官吏。宴会结束后，各自奏报群臣的过失，瞪眼的过错，说错话的罪过，没有不被举报的。大的过失就施加酷刑，小的过失也定为罪名。后宫有数千人，而采选美女没有停止。又引水入宫，宫人中有不合心意的，就杀死后顺水冲走。有的剥人的脸皮，有的挖人的眼睛。岑昬阴险谄媚而受宠幸，官至九卿，喜欢兴办劳役，众人感到痛苦。因此上下离心，没有人肯为孙皓尽力，大概是积恶已极，不再能忍受命运的缘故。[吴国平定后，晋朝侍中庾峻等人问孙皓的侍中李仁说：听说吴主剥人脸皮，砍人脚，有这事吗？李仁说：这是传话的人说得过分了。君子厌恶处于下流，天下的恶事都归到他身上。大概就是这类事，如果真有，也不足为怪。过去唐尧、虞舜有五刑，夏商周有七辟，肉刑的制度，不算残酷。孙皓作为一国之主，掌握生杀大权，罪人触犯法律，加以惩罚，有什么可指责的！受尧诛杀的人不能没有怨恨，受桀赏赐的人不能没有羡慕，这是人之常情。又问说：听说归命侯厌恶别人横目逆视，都挖他们的眼睛，有这事吗？李仁说：也没有这事，是传言错误。《曲礼》说：看天子目光在衣领以下，看诸侯在面颊以下，看大夫在胸口以下，看士人则平视，可以在五步之内游目；看上级高于胸口就是傲慢，低于腰带就是忧愁，旁视就是邪视。按照礼制观看，高下不可不谨慎，何况是君主呢？看君主时目光相逆，这就是礼制所说的傲慢；傲慢就是无礼，无礼就是不臣，不臣就是犯罪，犯罪就陷入不测了。即使真有，又有什么过失？凡是李仁的回答，庾峻等人都认为很好，文字多不全部记载。]",
    "std_start_year": 264,
    "涉及的集团": [],
    "所属事件": [],
    "地理信息": [
      "扬州:丹杨郡:建业县"
    ],
    "是否本传": true
  },
  {
    "事件标题": "孙皓立十一王并大赦",
    "时间": "天纪四年春",
    "地点": "建业",
    "相关人物": [
      "孙皓"
    ],
    "原文": "四年春，立中山、代等十一王，大赦。",
    "事件翻译": "天纪四年春天，孙皓立中山王、代王等十一个王，并大赦天下。",
    "std_start_year": 280,
    "涉及的集团": [],
    "所属事件": [],
    "地理信息": [
      "扬州:丹杨郡:建业县"
    ],
    "是否本传": true
  },
  {
    "事件标题": "晋军攻吴，吴军土崩瓦解",
    "时间": "天纪四年",
    "地点": "吴国各地",
    "相关人物": [
      "王濬",
      "王彬",
      "杜预",
      "伍延",
      "张悌",
      "沈莹"
    ],
    "原文": "濬、彬所至，则土崩瓦解，靡有御者。预又斩江陵督伍延，浑复斩丞相张悌、丹杨太守沈莹等，所在战克。",
    "事件翻译": "王濬、王彬所到之处，吴军土崩瓦解，没有能抵抗的。杜预又斩杀江陵督伍延，王浑又斩杀丞相张悌、丹杨太守沈莹等人，晋军每战必胜。",
    "std_start_year": 280,
    "涉及的集团": [],
    "所属事件": [
      "jin_mie_wu"
    ],
    "地理信息": [
      "荆州:南郡:江陵县",
      "扬州:丹杨郡"
    ],
    "是否本传": false
  },
  {
    "事件标题": "张悌率军渡江迎战晋军",
    "时间": "天纪四年",
    "地点": "牛渚",
    "相关人物": [
      "张悌",
      "沈莹",
      "诸葛靓",
      "张乔",
      "张翰",
      "周浚",
      "薛胜",
      "蒋班"
    ],
    "原文": "[干宝晋纪曰：吴丞相军师张悌、护军孙震、丹杨太守沈莹帅众三万济江，围成阳都尉张乔於杨荷桥，众才七千，闭栅自守，举白接告降。吴副军师诸葛靓欲屠之，悌曰：强敌在前，不宜先事其小；且杀降不祥。靓曰：此等以救兵未至而力少，故且伪降以缓我，非来伏也。因其无战心而尽坑之，可以成三军之气。若舍之而前，必为后患。悌不从，抚之而进。与讨吴护军张翰、扬州刺史周浚成陈相对。沈莹领丹杨锐卒刀楯五千，号曰青巾兵，前后屡陷坚陈，於是以驰淮南军，三冲不动。退引乱，薛胜、蒋班因其乱而乘之，吴军以次土崩，将帅不能止，张乔又出其后，大败吴军于版桥，获悌、震、莹等。]",
    "事件翻译": "干宝《晋纪》记载：吴丞相军师张悌、护军孙震、丹杨太守沈莹率领三万军队渡江，在杨荷桥包围了成阳都尉张乔，张乔只有七千人，关闭营寨坚守，举起白旗请求投降。吴副军师诸葛靓想杀掉他们，张悌说：强敌在前，不宜先处理小事；而且杀降不祥。诸葛靓说：这些人因为救兵未到而力量薄弱，所以假投降来拖延我们，并非真心归顺。趁他们没有战心而全部坑杀，可以鼓舞三军士气。如果放过他们而前进，必成后患。张悌不听，安抚他们后继续前进。与讨吴护军张翰、扬州刺史周浚列阵相对。沈莹率领丹杨精锐刀楯兵五千人，号称青巾兵，此前多次攻陷坚固阵地，于是冲击淮南军，三次冲锋都未能动摇。退兵时阵型混乱，薛胜、蒋班趁乱进攻，吴军依次崩溃，将帅无法制止，张乔又从背后出击，在版桥大败吴军，俘获张悌、孙震、沈莹等人。",
    "std_start_year": 280,
    "涉及的集团": [],
    "所属事件": [
      "jin_mie_wu"
    ],
    "地理信息": [
      "扬州:丹杨郡:牛渚",
      "扬州:丹杨郡:杨荷桥",
      "扬州:丹杨郡:版桥"
    ],
    "是否本传": false
  },
  {
    "事件标题": "张悌论司马氏得民心及蜀汉必亡",
    "时间": "景元四年",
    "地点": "吴国",
    "相关人物": [
      "张悌",
      "吴人"
    ],
    "原文": "[襄阳记曰：悌字巨先，襄阳人，少有名理，孙休时为屯骑校尉。魏伐蜀，吴人问悌曰：司马氏得政以来，大难屡作，智力虽丰，而百姓未服也。今又竭其资力，远征巴蜀，兵劳民疲而不知恤，败於不暇，何以能济？昔夫差伐齐，非不克胜，所以危亡，不忧其本也，况彼之争地乎！悌曰：不然。曹操虽功盖中夏，威震四海，崇诈杖术，征伐无已，民畏其威，而不怀其德也。丕、叡承之，系以惨虐，内兴宫室，外惧雄豪，东西驰驱，无岁获安，彼之失民，为日久矣。司马懿父子，自握其柄，累有大功，除其烦苛而布其平惠，为之谋主而救其疾，民心归之，亦已久矣。故淮南三叛而腹心不扰，曹髦之死，四方不动，摧坚敌如折枯，荡异同如反掌，任贤使能，各尽其心，非智勇兼人，孰能如之？其威武张矣，本根固矣，群情服矣，奸计立矣。今蜀阉宦专朝，国无政令，而玩戎黩武，民劳卒弊，竞於外利，不脩守备。彼强弱不同，智算亦胜，因危而伐，殆其克乎！若其不克，不过无功，终无退北之忧，覆军之虑也，何为不可哉？昔楚剑利而秦昭惧，孟明用而晋人忧，彼之得志，故我之大患也。吴人笑其言，而蜀果降于魏。]",
    "事件翻译": "《襄阳记》记载：张悌字巨先，襄阳人，年少时就有名望和才理，孙休时任屯骑校尉。魏国伐蜀时，吴人问张悌：司马氏执政以来，多次发生大难，虽然智谋丰富，但百姓并未归服。如今又竭尽资力远征巴蜀，兵士疲劳百姓困苦却不知体恤，失败都来不及，怎能成功？从前夫差伐齐，并非不能取胜，之所以危亡，是因为不忧根本，何况他们争夺土地呢？张悌说：不对。曹操虽然功盖华夏，威震四海，但崇尚诈术，征伐不止，百姓畏惧他的威严，却不怀念他的恩德。曹丕、曹叡继承，更加惨虐，内兴宫室，外惧豪强，东西奔波，没有一年安宁，他们失去民心已经很久了。司马懿父子掌握权柄，屡建大功，废除烦苛而施行平惠，为百姓谋划而解救疾苦，民心归附也已经很久了。所以淮南三叛而腹心不扰，曹髦之死而四方不动，摧折强敌如折断枯枝，荡平异己如反掌，任用贤能，各尽其心，若非智勇兼备，谁能如此？他们的威武已张，根本已固，群情已服，奸计已立。如今蜀国宦官专权，国无政令，却穷兵黩武，民劳兵疲，竞逐外利，不修守备。他们强弱不同，智算也胜，趁危而伐，大概能攻克吧！如果不能攻克，不过无功，终究没有退败之忧、覆军之虑，为何不可？从前楚国剑利而秦昭王恐惧，孟明用而晋人忧虑，他们得志，正是我们的大患。吴人嘲笑他的话，而蜀国果然投降了魏国。",
    "std_start_year": 263,
    "涉及的集团": [],
    "所属事件": [
      "wei_mie_shu"
    ],
    "地理信息": [
      "荆州:襄阳郡:襄阳县"
    ],
    "是否本传": false
  },
  {
    "事件标题": "张悌率军渡江决战并战死",
    "时间": "天纪四年",
    "地点": "牛渚",
    "相关人物": [
      "张悌",
      "沈莹",
      "诸葛靓",
      "孙皓"
    ],
    "原文": "[晋来伐吴，皓使悌督沈莹、诸葛靓，率众三万渡江逆之。至牛渚，沈莹曰：晋治水军於蜀久矣，今倾国大举，万里齐力，必悉益州之众浮江而下。我上流诸军，无有戒备，名将皆死，幼少当任，恐边江诸城，尽莫能御也。晋之水军，必至於此矣！宜畜众力，待来一战。若胜之日，江西自清，上方虽坏，可还取之。今渡江逆战，胜不可保，若或摧丧，则大事去矣。悌曰：吴之将亡，贤愚所知，非今日也。吾恐蜀兵来至此，众心必骇惧，不可复整。今宜渡江，可用决战力争。若其败丧，则同死社稷，无所复恨。若其克胜，则北敌奔走，兵势万倍，便当乘威南上，逆之中道，不忧不破也。若如子计，恐行散尽，相与坐待敌到，君臣俱降，无复一人死难者，不亦辱乎！遂渡江战，吴军大败。诸葛靓与五六百人退走，使过迎悌，悌不肯去，靓自往牵之，谓曰：巨先，天下存亡有大数，岂卿一人所知，如何故自取死为？悌垂涕曰：仲思，今日是我死日也。且我作儿童时，便为卿家丞相所拔，常恐不得其死，负名贤知顾。今以身徇社稷，复何遁邪？莫牵曳之如是。靓流涕放之，去百馀步，已见为晋军所杀。]",
    "事件翻译": "晋国来伐吴，孙皓派张悌督率沈莹、诸葛靓，率领三万人渡江迎战。到达牛渚，沈莹说：晋国在蜀地训练水军很久了，如今倾国大举，万里齐力，必定尽起益州之众顺江而下。我们上流各军没有戒备，名将都已死去，幼少担当重任，恐怕沿江各城都不能抵御。晋国水军必定到达这里！应当积蓄兵力，等待来战。如果战胜，江西自然平定，上游即使被毁，还可以夺回。如今渡江迎战，胜败难保，如果失败，大事就完了。张悌说：吴国将亡，贤愚皆知，并非今日。我担心蜀兵到来，众人必定惊骇，无法再整。如今应当渡江，决战力争。如果失败，就同死社稷，无所遗憾。如果取胜，则北敌奔逃，兵势万倍，便当乘威南上，迎击于中道，不愁不破。如果按你的计策，恐怕兵士逃散，坐等敌人到来，君臣一起投降，没有一人死难，不也是耻辱吗！于是渡江决战，吴军大败。诸葛靓与五六百人退走，派人迎接张悌，张悌不肯离开，诸葛靓亲自去拉他，说：巨先，天下存亡自有天数，岂是你一人所知，为何自取死路？张悌流泪说：仲思，今日是我死日。我小时候就被你家丞相提拔，常恐不得善终，辜负名贤知遇。如今以身殉国，还逃什么呢？不要拉我了。诸葛靓流泪放手，走出百余步，已见张悌被晋军所杀。",
    "std_start_year": 280,
    "涉及的集团": [],
    "所属事件": [
      "jin_mie_wu"
    ],
    "地理信息": [
      "扬州:丹杨郡:牛渚"
    ],
    "是否本传": false
  },
  {
    "事件标题": "张悌生平及战死异闻",
    "时间": "天纪四年",
    "地点": "临海松阳",
    "相关人物": [
      "张悌",
      "柳荣"
    ],
    "原文": "[吴录曰：悌少知名，及处大任，希合时趣，将护左右，清论讥之。搜神记曰：临海松阳人柳荣从悌至杨府，荣病死船中二日，时军已上岸，无有埋之者，忽然大呼，言人缚军师！人缚军师！声激扬，遂活。人问之，荣曰：上天北斗门下卒见人缚张悌，意中大愕，不觉大呼，言何以缚张军师。门下人怒荣，叱逐使去。荣便去，怖惧，口馀声发扬耳。其日，悌战死。荣至晋元帝时犹在。]",
    "事件翻译": "《吴录》记载：张悌年少知名，等到担任大任，迎合时趣，庇护左右，清议讥讽他。《搜神记》记载：临海松阳人柳荣跟随张悌到杨府，柳荣在船中病死两天，当时军队已上岸，无人埋葬，他忽然大喊：有人绑了军师！有人绑了军师！声音激扬，于是复活。别人问他，柳荣说：上天北斗门下，我看见有人绑了张悌，心中大惊，不觉大喊：为什么绑张军师。门下人发怒，呵斥驱逐我。我便离开，恐惧，口中余声还在。当天，张悌战死。柳荣到晋元帝时还在世。",
    "std_start_year": 280,
    "涉及的集团": [],
    "所属事件": [
      "jin_mie_wu"
    ],
    "地理信息": [
      "扬州:丹杨郡:杨府",
      "扬州:会稽郡:临海县"
    ],
    "是否本传": false
  },
  {
    "事件标题": "孙皓杀岑昬",
    "时间": "天纪四年三月丙寅",
    "地点": "建业",
    "相关人物": [
      "孙皓",
      "岑昬"
    ],
    "原文": "三月丙寅，殿中亲近数百人叩头请皓杀岑昬，皓惶愦从之。[干宝晋纪曰：皓殿中亲近数百人叩头请皓曰：北军日近，而兵不举刃，陛下将如之何！皓曰：何故？对曰：坐岑昬。皓独言：若尔，当以奴谢百姓。众因曰：唯！遂并起收昬。皓骆驿追止，已屠之也。]",
    "事件翻译": "三月丙寅日，殿中亲近的数百人叩头请求孙皓杀死岑昬，孙皓惶恐糊涂地听从了。[干宝《晋纪》说：孙皓殿中亲近的数百人叩头请求孙皓说：北方的军队日益逼近，而我们的士兵却无法举起武器作战，陛下打算怎么办！孙皓说：为什么？回答说：因为岑昬。孙皓独自说：如果是这样，应当用这个奴才向百姓谢罪。众人于是说：是！就一起起身逮捕岑昬。孙皓派人接连追赶制止，但已经将他杀害了。]",
    "std_start_year": 280,
    "涉及的集团": [],
    "所属事件": [
      "jin_mie_wu"
    ],
    "地理信息": [
      "扬州:丹杨郡:建业县"
    ],
    "是否本传": true
  },
  {
    "事件标题": "孙皓在晋军压境时采纳薛莹、胡冲之计投降",
    "时间": "天纪四年（280年）",
    "地点": "建业",
    "相关人物": [
      "孙皓",
      "陶濬",
      "王濬",
      "司马伷",
      "王浑",
      "薛莹",
      "胡冲",
      "张夔"
    ],
    "原文": "戊辰，陶濬从武昌还，即引见，问水军消息，对曰：蜀船皆小，今得二万兵，乘大船战，自足击之。於是合众，授濬节钺。明日当发，其夜众悉逃走。而王濬顺流将至，司马伷、王浑皆临近境。皓用光禄勋薛莹、中书令胡冲等计，分遣使奉书於濬、伷、浑曰：昔汉室失统，九州分裂，先人因时，略有江南，遂分阻山川，与魏乖隔。今大晋龙兴，德覆四海。闇劣偷安，未喻天命。至于今者，猥烦六军，衡盖路次，远临江渚，举国震惶，假息漏刻。敢缘天朝含弘光大，谨遣私署太常张夔等奉所佩印绶，委质请命，惟垂信纳，以济元元。[江表传载皓将败与舅何植书曰：昔大皇帝以神武之略，奋三千之卒，割据江南，席卷交、广，开拓洪基，欲祚之万世。至孤末德，嗣守成绪，不能怀集黎元，多为咎阙，以违天度。闇昧之变，反谓之祥，致使南蛮逆乱，征讨未克。闻晋大众，远来临江，庶竭劳瘁，众皆摧退，而张悌不反，丧军过半。孤甚愧怅，于今无聊。得陶濬表云武昌以西，并复不守。不守者，非粮不足，非城不固，兵将背战耳。兵之背战，岂怨兵邪？孤之罪也。天文县变於上，士民愤叹於下，观此事势，危如累卵，吴祚终讫，何其局哉！天匪亡吴，孤所招也。瞑目黄壤，当复何颜见四帝乎！公其勖勉奇谟，飞笔以闻。皓又遗群臣书曰：孤以不德，忝继先轨。处位历年，政教凶勃，遂令百姓久困涂炭，至使一朝归命有道，社稷倾覆，宗庙无主，惭愧山积，没有馀罪。自惟空薄，过偷尊号，才琐质秽，任重王公，故周易有折鼎之诫，诗人有彼其之讥。自居宫室。仍抱笃疾，计有不足，思虑失中，多所荒替。边侧小人，因生酷虐，虐毒横流，忠顺被害。闇昧不觉，寻其壅蔽，孤负诸君，事已难图，覆水不可收也。今大晋平治四海，劳心务於擢贤，诚是英俊展节之秋也。管仲极雠，桓公用之，良、平去楚，入为汉臣，舍乱就理，非不忠也。莫以移朝改朔，用损厥志。嘉勖休尚，爱敬动静。夫复何言，投笔而已！]",
    "事件翻译": "戊辰日，陶濬从武昌返回，孙皓立即召见，询问水军情况，陶濬回答说：蜀地的船都很小，如今得到两万士兵，乘坐大船作战，足以击败他们。于是孙皓集合军队，授予陶濬符节和斧钺。准备第二天出发，但当天夜里士兵全部逃走。此时王濬顺流而下即将到达，司马伷、王浑也都逼近吴国边境。孙皓采纳光禄勋薛莹、中书令胡冲等人的计策，分别派遣使者送信给王濬、司马伷、王浑，信中说：从前汉朝失去统治，九州分裂，先人顺应时势，占据江南，于是凭借山川阻隔，与魏国隔绝。如今大晋兴起，恩德覆盖四海。我愚昧苟且偷安，不明白天命。直到现在，烦劳六军，车驾沿途，远临江边，全国震惊，苟延残喘。斗胆仰赖天朝包容光大，谨派私署太常张夔等人奉上所受的印绶，归顺请命，希望垂怜接纳，以拯救百姓。[江表传记载孙皓即将失败时写给舅舅何植的信说：从前大皇帝凭借神武的谋略，发动三千士兵，割据江南，席卷交州、广州，开拓宏伟基业，希望传位万世。到我德行浅薄，继承守成之业，不能安抚百姓，犯下许多过错，违背天意。把昏暗的变故反而当作祥瑞，致使南蛮叛乱，征讨未能成功。听说晋朝大军远来长江，我竭尽全力，军队却都溃退，而张悌没有返回，损失过半。我非常惭愧惆怅，如今无所依靠。得到陶濬的表章说武昌以西都已失守。失守的原因，不是粮食不足，不是城池不坚固，而是士兵将领不愿作战。士兵不愿作战，难道是怨恨士兵吗？是我的罪过啊。天象变异在上，士民愤叹在下，看这形势，危如累卵，吴国的国运终结，多么局促啊！上天并非要灭亡吴国，是我招来的。闭目于黄泉之下，还有什么脸面见四位先帝呢！您要勉力谋划奇策，迅速写信告知。孙皓又给群臣写信说：我以不德，愧继先业。在位多年，政教凶暴，致使百姓长久困于涂炭，以至于一朝归顺有道，社稷倾覆，宗庙无主，惭愧如山，死有余罪。自思空疏浅薄，窃居尊号，才能琐碎，品质卑劣，重任在身，所以《周易》有折鼎的告诫，《诗经》有彼其的讥讽。自居宫室，仍患重病，计谋不足，思虑失中，多有荒废。身边小人，因此产生酷虐，虐毒横流，忠顺被害。我昏昧不觉，被蒙蔽，辜负诸位，事情已难挽回，覆水不可收。如今大晋平定四海，劳心于选拔贤才，正是英俊施展节操之时。管仲曾是仇敌，齐桓公任用他；张良、陈平离开楚国，成为汉朝臣子，离开乱世归附治世，并非不忠。不要因为改朝换代而损害你们的志向。好好勉励，爱惜身体动静。还有什么可说，就此搁笔而已！]",
    "std_start_year": 280,
    "涉及的集团": [
      "jiang_dong"
    ],
    "所属事件": [
      "jin_mie_wu"
    ],
    "地理信息": [
      "扬州:丹杨郡:建业县",
      "荆州:江夏郡:武昌县"
    ],
    "是否本传": true
  },
  {
    "事件标题": "王濬受降孙皓",
    "时间": "咸宁六年（太康元年）",
    "地点": "建业",
    "相关人物": [
      "王濬",
      "孙皓",
      "司马伷",
      "王浑"
    ],
    "原文": "壬申，王濬最先到，於是受皓之降，解缚焚榇，延请相见。[晋阳秋曰：濬收其图籍，领州四，郡四十三，县三百一十三，户五十二万三千，吏三万二千，兵二十三万，男女口二百三十万，米谷二百八十万斛，舟船五千馀艘，后宫五千馀人。]伷以皓致印绶於己，遣使送皓。皓举家西迁，以太康元年五月丁亥集于京邑。四月甲申，诏曰：孙皓穷迫归降，前诏待之以不死，今皓垂至，意犹愍之，其赐号为归命侯。进给衣服车乘，田三十顷，岁给谷五千斛，钱五十万，绢五百匹，绵五百斤。皓太子瑾拜中郎，诸子为王者，拜郎中。[搜神记曰：吴以草创之国，信不坚固，边屯守将，皆质其妻子，名曰保质。童子少年，以类相与嬉游者，日有十数。永安二年三月，有一异儿，长四尺馀，年可六七岁，衣青衣，来从群儿戏，诸儿莫之识也。皆问曰：尔谁家小儿，今日忽来？答曰：见尔群戏乐，故来耳。详而视之，眼有光芒，爚爚外射。诸儿畏之，重问其故。儿乃答曰：尔恶我乎？我非人也，乃荧惑星也。将有以告尔：三公鉏，司马如。诸儿大惊，或走告大人，大人驰往观之。儿曰：舍尔去乎！竦身而跃，即以化矣。仰面视之，若引一匹练以登天。大人来者，犹及见焉，飘飘渐高，有顷而没。时吴政峻急，莫敢宣也。后五年而蜀亡，六年而晋兴，至是而吴灭，司马如矣。干宝晋纪曰：王濬治船於蜀，吾彦取其流柹以呈孙皓，曰：晋必有攻吴之计，宜增建平兵。建平不下，终不敢渡江。皓弗从。陆抗之克步阐，皓意张大，乃使尚广筮并天下，遇同人之颐，对曰：吉。庚子岁，青盖当入洛阳。故皓不脩其政，而恒有窥上国之志。是岁也实在庚子。]五年，皓死于洛阳。[吴录曰：皓以四年十二月死，时年四十二，葬河南县界。]",
    "事件翻译": "壬申日，王濬最先到达建业，于是接受孙皓的投降，解开捆绑的绳索，烧掉棺材，邀请孙皓相见。司马伷因为孙皓把印绶交给自己，便派人送孙皓去洛阳。孙皓全家西迁，于太康元年五月丁亥日到达京城。四月甲申日，晋武帝下诏说：孙皓走投无路归降，之前已下诏不杀他，现在孙皓即将到来，我心中怜悯他，赐给他归命侯的爵位。并赐给衣服车马、田地三十顷，每年供给谷物五千斛、钱五十万、绢五百匹、绵五百斤。孙皓的太子孙瑾被任命为中郎，其他封王的儿子被任命为郎中。五年后，孙皓在洛阳去世。",
    "std_start_year": 280,
    "涉及的集团": [],
    "所属事件": [
      "jin_mie_wu"
    ],
    "地理信息": [
      "扬州:丹杨郡:建业县",
      "司隶:河南尹:洛阳县"
    ],
    "是否本传": true
  }
]