[
  {
    "事件标题": "明帝即位",
    "时间": "黄初七年（226年）夏五月",
    "地点": "洛阳",
    "相关人物": [
      "明帝",
      "文帝"
    ],
    "事件简介": "魏文帝曹丕病重，立平原王曹叡为皇太子。文帝去世后，曹叡即皇帝位，大赦天下，尊奉皇太后和皇后，并封赏群臣。",
    "事件类型": "政治谋略",
    "影响/结果": "曹叡成为曹魏第二位皇帝，是为魏明帝，开启了明帝时代。",
    "原文": "七年夏五月，帝病笃，乃立为皇太子。丁巳，即皇帝位，大赦。尊皇太后曰太皇太后，皇后曰皇太后。诸臣封爵各有差。",
    "std_start_year": 226,
    "std_end_year": 226,
    "is_time_fuzzy": false
  },
  {
    "事件标题": "追谥生母甄氏",
    "时间": "黄初七年（226年）",
    "地点": "洛阳",
    "相关人物": [
      "明帝",
      "甄夫人"
    ],
    "事件简介": "明帝即位后，追谥自己的生母甄夫人为文昭皇后。",
    "事件类型": "政治谋略",
    "影响/结果": "确立了明帝生母的尊贵地位，符合礼制。",
    "原文": "癸未，追谥母甄夫人曰文昭皇后。",
    "std_start_year": 226,
    "std_end_year": 226,
    "is_time_fuzzy": false
  },
  {
    "事件标题": "判断孙权攻江夏",
    "时间": "黄初七年（226年）八月",
    "地点": "洛阳",
    "相关人物": [
      "明帝",
      "孙权",
      "文聘"
    ],
    "事件简介": "孙权攻打江夏郡，太守文聘坚守。朝廷商议发兵救援，明帝分析孙权擅长水战，此次登陆进攻是想趁人不备，既然已与文聘相持，攻守形势不同，孙权不敢久留。后来荀禹在江夏组织兵力虚张声势，孙权果然退走。",
    "事件类型": "军事征伐",
    "影响/结果": "明帝准确判断敌情，未劳师动众便化解了危机，孙权退兵。",
    "原文": "八月，孙权攻江夏郡，太守文聘坚守。朝议欲发兵救之，帝曰：\"权习水战，所以敢下船陆攻者，几掩不备也。今已与聘相持，夫攻守势倍，终不敢久也。\"先时遣治书侍御史荀禹慰劳边方，禹到，於江夏发所经县兵及所从步骑千人乘山举火，权退走。",
    "std_start_year": 226,
    "std_end_year": 226,
    "is_time_fuzzy": false
  },
  {
    "事件标题": "下诏讨伐孟达",
    "时间": "太和元年（227年）十二月",
    "地点": "洛阳",
    "相关人物": [
      "明帝",
      "孟达",
      "司马宣王"
    ],
    "事件简介": "新城太守孟达反叛，明帝下诏命令骠骑将军司马懿讨伐他。",
    "事件类型": "内政治理",
    "影响/结果": "司马懿迅速出兵，于次年正月攻破新城，斩杀孟达。",
    "原文": "新城太守孟达反，诏骠骑将军司马宣王讨之。",
    "std_start_year": 227,
    "std_end_year": 227,
    "is_time_fuzzy": false
  },
  {
    "事件标题": "决策抵御诸葛亮首次北伐",
    "时间": "太和二年（228年）",
    "地点": "洛阳",
    "相关人物": [
      "明帝",
      "诸葛亮",
      "曹真",
      "张郃"
    ],
    "事件简介": "蜀汉大将诸葛亮出兵北伐，天水、南安、安定三郡叛魏响应。朝臣不知所措，明帝分析诸葛亮是自投罗网，贪图三郡而不知进退，正是击败他的好时机。于是部署五万兵马，派大将军曹真都督关右诸军，右将军张郃在街亭大破诸葛亮。",
    "事件类型": "军事征伐",
    "影响/结果": "诸葛亮战败撤退，三郡被平定，明帝亲临长安。",
    "原文": "蜀大将诸葛亮寇边，天水、南安、安定三郡吏民叛应亮。【魏书曰：是时朝臣未知计所出，帝曰：\"亮阻山为固，今者自来，既合兵书致人之术；且亮贪三郡，知进而不知退，今因此时，破亮必也。\"乃部勒兵马步骑五万拒亮。】遣大将军曹真都督关右，并进兵。右将军张郃击亮於街亭，大破之。亮败走，三郡平。丁未，行幸长安。",
    "std_start_year": 228,
    "std_end_year": 228,
    "is_time_fuzzy": false
  },
  {
    "事件标题": "下诏尊儒贵学",
    "时间": "太和二年（228年）六月",
    "地点": "洛阳",
    "相关人物": [
      "明帝"
    ],
    "事件简介": "明帝下诏，认为尊崇儒学、重视教育是王教的根本。近来有些儒官不称职，无法宣扬圣道。命令严格选拔博士，并敕令各郡国荐举人才以通晓经学为先。",
    "事件类型": "内政治理",
    "影响/结果": "旨在整顿教育，选拔真正有学识的儒生，弘扬儒家学说。",
    "原文": "六月，诏曰：\"尊儒贵学，王教之本也。自顷儒官或非其人，将何以宣明圣道？其高选博士，才任侍中、常侍者。申敕郡国，贡士以经学为先。\"",
    "std_start_year": 228,
    "std_end_year": 228,
    "is_time_fuzzy": false
  },
  {
    "事件标题": "下诏明确继统礼法",
    "时间": "太和三年（229年）秋七月",
    "地点": "洛阳",
    "相关人物": [
      "明帝"
    ],
    "事件简介": "明帝下诏，依据礼法，如果皇后无子，应选择宗室支子继承大宗，这才算是继承正统、奉行公义，不能只顾私亲。他引用汉朝的历史教训，严令后世如果有由诸侯入继大统的，必须明确作为人后的道义。如有奸臣谄媚君主，妄称生父为皇、生母为后，干扰正统，大臣应诛杀无赦。并将此令刻于金策，藏于宗庙，写入法典。",
    "事件类型": "政治谋略",
    "影响/结果": "确立了曹魏政权宗法继承的根本原则，防止因私亲乱统。",
    "原文": "秋七月，诏曰：\"礼，王后无嗣，择建支子以继大宗，则当纂正统而奉公义，何得复顾私亲哉！...其令公卿有司，深以前世行事为戒。后嗣万一有由诸侯入奉大统，则当明为人后之义；敢为佞邪导谀时君，妄建非正之号以干正统，谓考为皇，称妣为后，则股肱大臣，诛之无赦。其书之金策，藏之宗庙，著於令典。\"",
    "std_start_year": 229,
    "std_end_year": 229,
    "is_time_fuzzy": false
  },
  {
    "事件标题": "重视刑狱，临听讼观",
    "时间": "太和三年（229年）冬十月",
    "地点": "洛阳",
    "相关人物": [
      "明帝"
    ],
    "事件简介": "明帝将平望观改名为听讼观。他常说“刑狱关系到天下的性命”，每次审理重大案件，常常亲临听讼观旁听。",
    "事件类型": "内政治理",
    "影响/结果": "体现了明帝对司法审判的重视，意图通过亲临监督来确保刑狱的公正。",
    "原文": "冬十月，改平望观曰听讼观。帝常言\"狱者，天下之性命也\"，每断大狱，常幸观临听之。",
    "std_start_year": 229,
    "std_end_year": 229,
    "is_time_fuzzy": false
  },
  {
    "事件标题": "下诏整顿郎吏选拔",
    "时间": "太和四年（230年）春二月",
    "地点": "洛阳",
    "相关人物": [
      "明帝"
    ],
    "事件简介": "明帝下诏，认为世风质朴或华美随教化而变。战乱以来经学废绝，年轻人求取仕进不通过经典。这恐怕是训导不够，或者选拔人才不看重德行。命令郎吏中通晓一经、有才能治理百姓的，博士考试中成绩优异者，立即任用；那些浮华不务根本的，一律罢退。",
    "事件类型": "政治谋略",
    "影响/结果": "旨在纠正浮华风气，强调经学和德行在官员选拔中的重要性。",
    "原文": "四年春二月壬午，诏曰：\"世之质文，随教而变。兵乱以来，经学废绝，后生进趣，不由典谟。岂训导未洽，将进用者不以德显乎？其郎吏学通一经，才任牧民，博士课试，擢其高第者，亟用；其浮华不务道本者，皆罢退之。\"",
    "std_start_year": 230,
    "std_end_year": 230,
    "is_time_fuzzy": false
  },
  {
    "事件标题": "决策抵御诸葛亮第四次北伐",
    "时间": "太和五年（231年）",
    "地点": "洛阳",
    "相关人物": [
      "明帝",
      "诸葛亮",
      "司马宣王"
    ],
    "事件简介": "诸葛亮再次出兵进攻天水。明帝下诏命大将军司马懿率军抵御。有人建议收割上邽附近的麦子以断蜀军粮草，明帝不同意，反而派兵保护麦田，并增兵给司马懿。最终司马懿凭借这些麦子作为军粮，与诸葛亮相持，直至诸葛亮粮尽退兵。",
    "事件类型": "军事征伐",
    "影响/结果": "诸葛亮退兵，明帝对有功将士封赏。",
    "原文": "诸葛亮寇天水，诏大将军司马宣王拒之。...【魏书曰：初，亮出，议者以为亮军无辎重，粮必不继，不击自破，无为劳兵；或欲自芟上邽左右生麦以夺贼食，帝皆不从。前后遣兵增宣王军，又敕使护麦。宣王与亮相持，赖得此麦以为军粮。】",
    "std_start_year": 231,
    "std_end_year": 231,
    "is_time_fuzzy": false
  },
  {
    "事件标题": "下诏允许诸王遣子朝觐",
    "时间": "太和五年（231年）八月",
    "地点": "洛阳",
    "相关人物": [
      "明帝"
    ],
    "事件简介": "明帝下诏，说古代诸侯朝聘是为了敦睦亲情、协和万国。先帝（曹丕）下令不让诸王留在京城，是考虑到幼主在位、母后摄政，需要防微杜渐。明帝说自己已十二年未见诸王，心中思念，因此命令诸王及宗室公侯各派嫡子一人入朝。但以后若有少主、母后在宫的情况，仍按先帝法令执行。",
    "事件类型": "政治谋略",
    "影响/结果": "在防范宗室干政与维系亲情之间寻求平衡，暂时放宽了对诸王的限制。",
    "原文": "八月，诏曰：\"古者诸侯朝聘，所以敦睦亲亲协和万国也。先帝著令，不欲使诸王在京都者，谓幼主在位，母后摄政，防微以渐，关诸盛衰也。朕惟不见诸王十有二载，悠悠之怀，能不兴思！其令诸王及宗室公侯各将適子一人朝。后有少主、母后在宫者，自如先帝令，申明著于令。\"",
    "std_start_year": 231,
    "std_end_year": 231,
    "is_time_fuzzy": false
  },
  {
    "事件标题": "下诏改封诸侯以郡为国",
    "时间": "太和六年（232年）春二月",
    "地点": "洛阳",
    "相关人物": [
      "明帝"
    ],
    "事件简介": "明帝下诏，认为古代帝王封建诸侯是为了藩屏王室。秦、汉继承周制，但封建的诸侯或强或弱，都不适中。大魏创业时诸王开国，制度未定，不能作为永久法则。因此命令改封诸侯王，都以郡作为封国。",
    "事件类型": "政治谋略",
    "影响/结果": "改革了诸侯王的封国制度，试图使之更规范化，加强中央对地方的控制。",
    "原文": "六年春二月，诏曰：\"古之帝王，封建诸侯，所以藩屏王室也。...大魏创业，诸王开国，随时之宜，未有定制，非所以永为后法也。其改封诸侯王，皆以郡为国。\"",
    "std_start_year": 232,
    "std_end_year": 232,
    "is_time_fuzzy": false
  },
  {
    "事件标题": "观龙改元",
    "时间": "青龙元年（233年）春",
    "地点": "摩陂",
    "相关人物": [
      "明帝"
    ],
    "事件简介": "有青龙出现在郏县的摩陂井中。二月，明帝亲临摩陂观看青龙，于是将年号改为“青龙”，改摩陂为龙陂，赏赐天下男子爵位二级，鳏寡孤独免除当年租赋。",
    "事件类型": "方技文化与礼制",
    "影响/结果": "因祥瑞出现而更改年号，并施恩于民。",
    "原文": "青龙元年春正月甲申，青龙见郏之摩陂井中。二月丁酉，幸摩陂观龙，於是改年；改摩陂为龙陂，赐男子爵人二级，鳏寡孤独无出今年租赋。",
    "std_start_year": 233,
    "std_end_year": 233,
    "is_time_fuzzy": false
  },
  {
    "事件标题": "否决毕轨出兵计划",
    "时间": "青龙元年（233年）",
    "地点": "洛阳",
    "相关人物": [
      "明帝",
      "毕轨",
      "步度根",
      "轲比能"
    ],
    "事件简介": "并州刺史毕轨上表，请求出兵对外威慑叛乱的鲜卑首领轲比能，对内镇抚保塞的鲜卑首领步度根。明帝看了奏表后说：“步度根已经被轲比能引诱，心有疑虑。现在毕轨出兵，正好促使两部惊慌之下合为一体，还谈什么威慑镇抚？”于是紧急命令毕轨，已出兵的部队千万不要越过句注塞。但诏书到达时，毕轨已经进军屯驻阴馆，并派兵追击鲜卑，结果战败，步度根部落全部叛逃出塞与轲比能会合侵扰边境。明帝派秦朗率军讨伐，敌人才逃往漠北。",
    "事件类型": "军事征伐",
    "影响/结果": "明帝准确预判了局势，但命令未能及时阻止毕轨的冒进行动，导致边境鲜卑势力联合为患。",
    "原文": "保塞鲜卑大人步度根与叛鲜卑大人轲比能私通，并州刺史毕轨表，辄出军以外威比能，内镇步度根。帝省表曰：\"步度根以为比能所诱，有自疑心。今轨出军，適使二部惊合为一，何所威镇乎？\"促敕轨，以出军者慎勿越塞过句注也。比诏书到，轨以进军屯阴馆，遣将军苏尚、董弼追鲜卑。比能遣子将千馀骑迎步度根部落，与尚、弼相遇，战於楼烦，二将败没。步度根部落皆叛出塞，与比能合寇边。遣骁骑将军秦朗将中军讨之，虏乃走漠北。",
    "std_start_year": 233,
    "std_end_year": 233,
    "is_time_fuzzy": false
  },
  {
    "事件标题": "决策抵御诸葛亮第五次北伐",
    "时间": "青龙二年（234年）",
    "地点": "洛阳",
    "相关人物": [
      "明帝",
      "诸葛亮",
      "司马宣王"
    ],
    "事件简介": "诸葛亮出兵斜谷，屯驻渭南，司马懿率诸军抵御。明帝下诏给司马懿：“只需坚守营垒挫其锐气，他进不能得志，退又无人与他交战，时间一长粮食耗尽，抢掠无获，就一定会撤退。等他撤退时再追击，以逸待劳，这是全胜之道。”后来诸葛亮多次挑战，司马懿坚守不出，直至诸葛亮病逝军中，蜀军撤退。",
    "事件类型": "军事征伐",
    "影响/结果": "明帝制定了正确的持久防御战略，司马懿严格执行，最终诸葛亮病逝，蜀军无功而返。",
    "原文": "是月，诸葛亮出斜谷，屯渭南，司马宣王率诸军拒之。诏宣王：\"但坚壁拒守以挫其锋，彼进不得志，退无与战，久停则粮尽，虏略无所获，则必走矣。走而追之，以逸待劳，全胜之道也。\"",
    "std_start_year": 234,
    "std_end_year": 234,
    "is_time_fuzzy": false
  },
  {
    "事件标题": "决策并亲征抵御孙权",
    "时间": "青龙二年（234年）",
    "地点": "合肥新城、寿春",
    "相关人物": [
      "明帝",
      "孙权",
      "满宠",
      "陆议",
      "孙韶"
    ],
    "事件简介": "孙权进军巢湖口，指向合肥新城，又派陆议、孙韶各率万余人进入淮河、沔水一带。征东将军满宠建议放弃新城，引诱吴军到寿春再决战。明帝不同意，认为合肥等战略要地是必争之处，孙权必定攻不下新城。他命令诸将坚守，自己将亲征。七月，明帝亲乘龙舟东征。吴军攻打新城，守将张颖等力战。明帝大军未到数百里，孙权就逃走了，陆议、孙韶也退兵。群臣建议明帝西去长安督战诸葛亮，明帝认为孙权已走，诸葛亮吓破了胆，有司马懿对付，自己无需担忧。于是进军寿春，论功行赏。",
    "事件类型": "军事征伐",
    "影响/结果": "明帝力排众议，坚持防守战略要地，并果断亲征，迫使孙权退兵，稳定了东部战线。",
    "原文": "孙权入居巢湖口，向合肥新城，又遣将陆议、孙韶各将万馀人入淮、沔。六月，征东将军满宠进军拒之。宠欲拔新城守，致贼寿春，帝不听，曰：\"昔汉光武遣兵县据略阳，终以破隗嚣，先帝东置合肥，南守襄阳，西固祁山，贼来辄破於三城之下者，地有所必争也。纵权攻新城，必不能拔。敕诸将坚守，吾将自往征之，比至，恐权走也。\"秋七月壬寅，帝亲御龙舟东征，权攻新城，将军张颖等拒守力战，帝军未至数百里，权遁走，议、韶等亦退。群臣以为大将军方与诸葛亮相持未解，车驾可西幸长安。帝曰：\"权走，亮胆破，大将军以制之，吾无忧矣。\"遂进军幸寿春，录诸将功，封赏各有差。",
    "std_start_year": 234,
    "std_end_year": 234,
    "is_time_fuzzy": false
  },
  {
    "事件标题": "大治洛阳宫室引直臣谏",
    "时间": "青龙三年（235年）",
    "地点": "洛阳",
    "相关人物": [
      "明帝",
      "杨阜",
      "高堂隆"
    ],
    "事件简介": "当时，明帝大规模修建洛阳宫，兴建昭阳殿、太极殿，修筑总章观。工程导致百姓耽误农时。直臣杨阜、高堂隆等人多次恳切劝谏。明帝虽然没有听从他们的意见，但常常宽容对待他们。",
    "事件类型": "内政治理",
    "影响/结果": "宫室修建耗费巨大，影响民生，虽遭直臣反对，但明帝并未停止工程，只是对谏者保持表面上的优容。",
    "原文": "是时，大治洛阳宫，起昭阳、太极殿，筑总章观。百姓失农时，直臣杨阜、高堂隆等各数切谏，虽不能听，常优容之。",
    "std_start_year": 235,
    "std_end_year": 235,
    "is_time_fuzzy": false
  },
  {
    "事件标题": "下诏议狱缓死",
    "时间": "青龙四年（236年）六月",
    "地点": "洛阳",
    "相关人物": [
      "明帝"
    ],
    "事件简介": "明帝下诏，认为法令越详明，犯法的人越多，刑罚越重，奸邪却止不住。之前已经减免了许多死刑条款，意在拯救百姓性命。但郡国一年中判决的死刑案件仍有过百，他反思是否是教导不淳厚使民轻罪，或是苛刻的法令犹存如同陷阱。命令司法官员审议案件，减缓死刑，务求宽简。对于乞求恩赦的案件，有的犯人陈词还未说完判决就已下达，这不能彻底审理案情。因此命令廷尉及天下狱官，所有死罪案件审定后，除非是谋反和亲手杀人，都要告知犯人家属，如有乞恩者，将乞恩文书与判决文书一同上奏，明帝将考虑如何保全其性命。并布告天下，使百姓明白他的心意。",
    "事件类型": "内政治理",
    "影响/结果": "体现了明帝慎刑恤狱的思想，试图减少死刑，完善死刑复核和乞恩程序。",
    "原文": "六月壬申，诏曰：\"有虞氏画象而民弗犯，周人刑错而不用。朕从百王之末，追望上世之风，邈乎何相去之远？法令滋章，犯者弥多，刑罚愈众，而奸不可止。...其令廷尉及天下狱官，诸有死罪具狱以定，非谋反及手杀人，亟语其亲治，有乞恩者，使与奏当文书俱上，朕将思所以全之。其布告天下，使明朕意。\"",
    "std_start_year": 236,
    "std_end_year": 236,
    "is_time_fuzzy": false
  },
  {
    "事件标题": "定历改元景初",
    "时间": "景初元年（237年）三月",
    "地点": "洛阳",
    "相关人物": [
      "明帝"
    ],
    "事件简介": "因有司奏报魏得地统，应改用殷历，以建丑之月（农历十二月）为正月。明帝依据古典，下诏改青龙五年三月为景初元年四月，更改历法，服色尚黄，牺牲用白，军旅乘黑头白马，建大红旗，朝会建大白旗，改太和历为景初历。",
    "事件类型": "政治谋略",
    "影响/结果": "进行了大规模的礼制改革，通过改正朔、易服色来彰显曹魏受命于天的正统性。",
    "原文": "景初元年春正月壬辰，山茌县言黄龙见。於是有司奏，以为魏得地统，宜以建丑之月为正。三月，定历改年为孟夏四月。...服色尚黄，牺牲用白，戎事乘黑首白马，建大赤之旂，朝会建大白之旗。改太和历曰景初历。",
    "std_start_year": 237,
    "std_end_year": 237,
    "is_time_fuzzy": false
  },
  {
    "事件标题": "议定三祖庙乐",
    "时间": "景初元年（237年）",
    "地点": "洛阳",
    "相关人物": [
      "明帝"
    ],
    "事件简介": "有司上奏：武皇帝曹操拨乱反正，为魏太祖，乐用《武始之舞》；文皇帝曹丕应天受命，为魏高祖，乐用《咸熙之舞》；当今皇帝（明帝）制作兴治，为魏烈祖，乐用《章斌之舞》。三祖之庙，万世不毁。其余四庙，亲缘尽则依次迁毁，如同周朝后稷、文王、武王庙的制度。明帝同意。",
    "事件类型": "方技文化与礼制",
    "影响/结果": "确立了曹操、曹丕、曹叡三人“三祖”的庙号和在宗庙中的永久地位，构建了曹魏的宗庙祭祀体系。",
    "原文": "有司奏：武皇帝拨乱反正，为魏太祖，乐用武始之舞。文皇帝应天受命，为魏高祖，乐用咸熙之舞。帝制作兴治，为魏烈祖，乐用章【武】斌之舞。三祖之庙，万世不毁。其馀四庙，亲尽迭毁，如周后稷、文、武庙祧之制。",
    "std_start_year": 237,
    "std_end_year": 237,
    "is_time_fuzzy": false
  },
  {
    "事件标题": "决策讨伐公孙渊",
    "时间": "景初元年（237年）至二年（238年）",
    "地点": "洛阳",
    "相关人物": [
      "明帝",
      "公孙渊",
      "司马宣王"
    ],
    "事件简介": "公孙渊反叛，自立为燕王。明帝决议派太尉司马懿率军四万讨伐。有大臣认为四万兵多，后勤难以供应。明帝说：“四千里远征，虽要用奇，也需足够兵力，不应过于计较费用。”于是派四万人出征。司马懿到辽东后，遇大雨无法进攻，有大臣建议召司马懿回师。明帝说：“司马懿临危制变，擒获公孙渊指日可待。”后来果然如明帝所料，司马懿攻破襄平，斩杀公孙渊。",
    "事件类型": "军事征伐",
    "影响/结果": "明帝力排众议，坚持派出足够兵力并信任主帅，最终平定辽东，消灭了公孙渊割据势力。",
    "原文": "初，帝议遣宣王讨渊，发卒四万人。议臣皆以为四万兵多，役费难供。帝曰：\"四千里征伐，虽云用奇，亦当任力，不当稍计役费。\"遂以四万人行。及宣王至辽东，霖雨不得时攻，群臣或以为渊未可卒破，宜诏宣王还。帝曰：\"司马懿临危制变，擒渊可计日待也。\"卒皆如所策。",
    "std_start_year": 237,
    "std_end_year": 238,
    "is_time_fuzzy": false
  },
  {
    "事件标题": "病重托孤",
    "时间": "景初三年（239年）春正月",
    "地点": "洛阳嘉福殿",
    "相关人物": [
      "明帝",
      "司马宣王",
      "曹爽"
    ],
    "事件简介": "明帝病重，从河内紧急召回太尉司马懿，将他引入卧室内，握着他的手说：“我病得很重，后事就托付给你了，你要和曹爽一起辅佐幼主。我能见到你，没有遗憾了！”司马懿叩头流泪。当日，明帝在嘉福殿去世，年仅三十六岁。",
    "事件类型": "政治谋略",
    "影响/结果": "明帝指定司马懿和曹爽为顾命大臣，辅佐年幼的齐王曹芳。这为后来曹魏政权的动荡埋下了伏笔。",
    "原文": "三年春正月丁亥，太尉宣王还至河内，帝驿马召到，引入卧内，执其手谓曰：\"吾疾甚，以后事属君，君其与爽辅少子。吾得见君，无所恨！\"宣王顿首流涕。...即日，帝崩于嘉福殿，时年三十六。",
    "std_start_year": 239,
    "std_end_year": 239,
    "is_time_fuzzy": false
  }
]