[
  {
    "事件标题": "陈留王奂被迎立为帝",
    "时间": "景元元年（260年）六月甲寅",
    "地点": "洛阳",
    "相关人物": [
      "陈留王奂",
      "皇太后",
      "公卿"
    ],
    "事件简介": "高贵乡公曹髦被杀后，公卿大臣们商议决定迎立陈留王曹奂为帝。六月甲寅日，曹奂进入洛阳，拜见皇太后，并在太极前殿即皇帝位。他下令大赦天下，改换年号，并赏赐百姓爵位、粮食和布帛。",
    "事件类型": "政治谋略",
    "影响/结果": "曹奂成为曹魏的末代皇帝，但此时朝政大权已完全掌握在司马氏手中，他只是一个名义上的君主。",
    "原文": "陈留王讳奂，字景明，武帝孙，燕王宇子也。甘露三年，封安次县常道乡公。高贵乡公卒，公卿议迎立公。六月甲寅，入于洛阳，见皇太后，是日即皇帝位于太极前殿，大赦，改年，赐民爵及谷帛各有差。",
    "std_start_year": 260,
    "std_end_year": 260,
    "is_time_fuzzy": false
  },
  {
    "事件标题": "下诏禅位于晋",
    "时间": "咸熙二年（265年）十二月",
    "地点": "洛阳南郊、金墉城、邺城",
    "相关人物": [
      "陈留王奂",
      "晋王司马炎",
      "群公卿士"
    ],
    "事件简介": "在司马昭去世，其子司马炎继承晋王之位后，曹魏的国运已尽。曹奂下诏，命令公卿大臣在南郊设立祭坛，派遣使者捧着皇帝的玉玺、绶带和册书，将帝位禅让给晋王司马炎，完全仿照汉朝禅让给曹魏的旧例。禅让仪式完成后，曹奂离开皇宫，先搬到金墉城暂住，最后定居在邺城，结束了皇帝生涯。",
    "事件类型": "内政治理",
    "影响/结果": "曹魏政权正式灭亡，司马炎建立晋朝（西晋），中国历史进入一个新的时期。曹奂被废后，被封为陈留王。",
    "原文": "十二月壬戌，天禄永终，历数在晋。诏群公卿士具仪设坛于南郊，使使者奉皇帝玺绶册，禅位于晋嗣王，如汉魏故事。甲子，使使者奉策。遂改次于金墉城，而终馆于邺，时年二十。",
    "std_start_year": 265,
    "std_end_year": 265,
    "is_time_fuzzy": false
  }
]